Workbook

Sheet GASTOS
C8: RESUMEN ANUAL
A10: FECHA | B10: REFERENCIA | C10: DESCRIPCIÓN | D10: MONTO BS | E10: D/C | F10: COD/CONT | G10: CONTABLE | H10: Deposito | I10: Codigo Dep | J10: Campaña | K10: PROVEEDOR | L10: Columna2 | M10: COD/SER | N10: SERVICIO | O10: Columna1 | P10: TASA | Q10: MONTO EN $ | R10: BANCO | S10: OBSERVACIONES | T10: NªGASTO | U10: Nº | V10: CLASIFICACION | W10: SEDE
A11: 46030 | B11: 13264946969 | C11: COM. TRF. CR.INM.OB | D11: -768.54 | E11: D | F11: =VLOOKUP(Tabla3[[#This Row],[CONTABLE]],'SAPROV (2)'!L:M,2,FALSE) -> #N/A | H11: ADMINISTRATIVOS | I11: =VLOOKUP(Tabla3[[#This Row],[Deposito]],'SAPROV (2)'!D:E,2,FALSE) -> A01 | K11: COMISIONES BANCARIAS | L11: =VLOOKUP(Tabla3[[#This Row],[PROVEEDOR]],'SAPROV (2)'!A:B,2,FALSE) -> 04 | M11: =VLOOKUP(Tabla3[[#This Row],[SERVICIO]],'SAPROV (2)'!I:J,2,FALSE) -> SERV0060 | N11: ?COMISIONES BANCARIAS | P11: =VLOOKUP(Tabla3[[#This Row],[FECHA]],TASA[],2,FALSE) -> 321.03 | Q11: =D11/P11 -> -2.3939819 | R11: BANESCO
A12: 46030 | B12: 13264948035 | C12: COM. TRF. CR.INM.OB | D12: -422.7 | E12: D | F12: =VLOOKUP(Tabla3[[#This Row],[CONTABLE]],'SAPROV (2)'!L:M,2,FALSE) -> #N/A | H12: ADMINISTRATIVOS | I12: =VLOOKUP(Tabla3[[#This Row],[Deposito]],'SAPROV (2)'!D:E,2,FALSE) -> A01 | K12: COMISIONES BANCARIAS | L12: =VLOOKUP(Tabla3[[#This Row],[PROVEEDOR]],'SAPROV (2)'!A:B,2,FALSE) -> 04 | M12: =VLOOKUP(Tabla3[[#This Row],[SERVICIO]],'SAPROV (2)'!I:J,2,FALSE) -> SERV0060 | N12: ?COMISIONES BANCARIAS | P12: =VLOOKUP(Tabla3[[#This Row],[FECHA]],TASA[],2,FALSE) -> 321.03 | Q12: =D12/P12 -> -1.3166994 | R12: BANESCO
A13: 46030 | B13: 13264948745 | C13: COM. TRF. CR.INM.OB | D13: -238.08 | E13: D | F13: =VLOOKUP(Tabla3[[#This Row],[CONTABLE]],'SAPROV (2)'!L:M,2,FALSE) -> #N/A | H13: ADMINISTRATIVOS | I13: =VLOOKUP(Tabla3[[#This Row],[Deposito]],'SAPROV (2)'!D:E,2,FALSE) -> A01 | K13: COMISIONES BANCARIAS | L13: =VLOOKUP(Tabla3[[#This Row],[PROVEEDOR]],'SAPROV (2)'!A:B,2,FALSE) -> 04 | M13: =VLOOKUP(Tabla3[[#This Row],[SERVICIO]],'SAPROV (2)'!I:J,2,FALSE) -> SERV0060 | N13: ?COMISIONES BANCARIAS | P13: =VLOOKUP(Tabla3[[#This Row],[FECHA]],TASA[],2,FALSE) -> 321.03 | Q13: =D13/P13 -> -0.74161293 | R13: BANESCO
A14: 46030 | B14: 13264956402 | C14: COM. TRF. CR.INM.OB | D14: -548.36 | E14: D | F14: =VLOOKUP(Tabla3[[#This Row],[CONTABLE]],'SAPROV (2)'!L:M,2,FALSE) -> #N/A | H14: ADMINISTRATIVOS | I14: =VLOOKUP(Tabla3[[#This Row],[Deposito]],'SAPROV (2)'!D:E,2,FALSE) -> A01 | K14: COMISIONES BANCARIAS | L14: =VLOOKUP(Tabla3[[#This Row],[PROVEEDOR]],'SAPROV (2)'!A:B,2,FALSE) -> 04 | M14: =VLOOKUP(Tabla3[[#This Row],[SERVICIO]],'SAPROV (2)'!I:J,2,FALSE) -> SERV0060 | N14: ?COMISIONES BANCARIAS | P14: =VLOOKUP(Tabla3[[#This Row],[FECHA]],TASA[],2,FALSE) -> 321.03 | Q14: =D14/P14 -> -1.708127 | R14: BANESCO
A15: 46031 | B15: 13265531340 | C15: COM. TRF. CR.INM.OB | D15: -3000 | E15: D | F15: =VLOOKUP(Tabla3[[#This Row],[CONTABLE]],'SAPROV (2)'!L:M,2,FALSE) -> #N/A | H15: ADMINISTRATIVOS | I15: =VLOOKUP(Tabla3[[#This Row],[Deposito]],'SAPROV (2)'!D:E,2,FALSE) -> A01 | K15: COMISIONES BANCARIAS | L15: =VLOOKUP(Tabla3[[#This Row],[PROVEEDOR]],'SAPROV (2)'!A:B,2,FALSE) -> 04 | M15: =VLOOKUP(Tabla3[[#This Row],[SERVICIO]],'SAPROV (2)'!I:J,2,FALSE) -> SERV0060 | N15: ?COMISIONES BANCARIAS | P15: =VLOOKUP(Tabla3[[#This Row],[FECHA]],TASA[],2,FALSE) -> 325.39 | Q15: =D15/P15 -> -9.2197056 | R15: BANESCO
A16: 46031 | B16: 13265532349 | C16: COM. TRF. CR.INM.OB | D16: -900 | E16: D | F16: =VLOOKUP(Tabla3[[#This Row],[CONTABLE]],'SAPROV (2)'!L:M,2,FALSE) -> #N/A | H16: ADMINISTRATIVOS | I16: =VLOOKUP(Tabla3[[#This Row],[Deposito]],'SAPROV (2)'!D:E,2,FALSE) -> A01 | K16: COMISIONES BANCARIAS | L16: =VLOOKUP(Tabla3[[#This Row],[PROVEEDOR]],'SAPROV (2)'!A:B,2,FALSE) -> 04 | M16: =VLOOKUP(Tabla3[[#This Row],[SERVICIO]],'SAPROV (2)'!I:J,2,FALSE) -> SERV0060 | N16: ?COMISIONES BANCARIAS | P16: =VLOOKUP(Tabla3[[#This Row],[FECHA]],TASA[],2,FALSE) -> 325.39 | Q16: =D16/P16 -> -2.7659117 | R16: BANESCO
A17: 46031 | B17: 13265533768 | C17: COM. TRF. CR.INM.OB | D17: -1500 | E17: D | F17: =VLOOKUP(Tabla3[[#This Row],[CONTABLE]],'SAPROV (2)'!L:M,2,FALSE) -> #N/A | H17: ADMINISTRATIVOS | I17: =VLOOKUP(Tabla3[[#This Row],[Deposito]],'SAPROV (2)'!D:E,2,FALSE) -> A01 | K17: COMISIONES BANCARIAS | L17: =VLOOKUP(Tabla3[[#This Row],[PROVEEDOR]],'SAPROV (2)'!A:B,2,FALSE) -> 04 | M17: =VLOOKUP(Tabla3[[#This Row],[SERVICIO]],'SAPROV (2)'!I:J,2,FALSE) -> SERV0060 | N17: ?COMISIONES BANCARIAS | P17: =VLOOKUP(Tabla3[[#This Row],[FECHA]],TASA[],2,FALSE) -> 325.39 | Q17: =D17/P17 -> -4.6098528 | R17: BANESCO
A18: 46035 | B18: 13266810676 | C18: COM. TRF. CR.INM.OB | D18: -2 | E18: D | F18: =VLOOKUP(Tabla3[[#This Row],[CONTABLE]],'SAPROV (2)'!L:M,2,FALSE) -> #N/A | H18: ADMINISTRATIVOS | I18: =VLOOKUP(Tabla3[[#This Row],[Deposito]],'SAPROV (2)'!D:E,2,FALSE) -> A01 | K18: COMISIONES BANCARIAS | L18: =VLOOKUP(Tabla3[[#This Row],[PROVEEDOR]],'SAPROV (2)'!A:B,2,FALSE) -> 04 | M18: =VLOOKUP(Tabla3[[#This Row],[SERVICIO]],'SAPROV (2)'!I:J,2,FALSE) -> SERV0060 | N18: ?COMISIONES BANCARIAS | P18: =VLOOKUP(Tabla3[[#This Row],[FECHA]],TASA[],2,FALSE) -> 330.38 | Q18: =D18/P18 -> -0.0060536352 | R18: BANESCO
A19: 46035 | B19: 13266838623 | C19: COM. TRF. CR.INM.OB | D19: -48.16 | E19: D | F19: =VLOOKUP(Tabla3[[#This Row],[CONTABLE]],'SAPROV (2)'!L:M,2,FALSE) -> #N/A | H19: ADMINISTRATIVOS | I19: =VLOOKUP(Tabla3[[#This Row],[Deposito]],'SAPROV (2)'!D:E,2,FALSE) -> A01 | K19: COMISIONES BANCARIAS | L19: =VLOOKUP(Tabla3[[#This Row],[PROVEEDOR]],'SAPROV (2)'!A:B,2,FALSE) -> 04 | M19: =VLOOKUP(Tabla3[[#This Row],[SERVICIO]],'SAPROV (2)'!I:J,2,FALSE) -> SERV0060 | N19: ?COMISIONES BANCARIAS | P19: =VLOOKUP(Tabla3[[#This Row],[FECHA]],TASA[],2,FALSE) -> 330.38 | Q19: =D19/P19 -> -0.14577154 | R19: BANESCO
A20: 46035 | B20: 13267182287 | C20: COM. TRF. CR.INM.OB | D20: -2759.29 | E20: D | F20: =VLOOKUP(Tabla3[[#This Row],[CONTABLE]],'SAPROV (2)'!L:M,2,FALSE) -> #N/A | H20: ADMINISTRATIVOS | I20: =VLOOKUP(Tabla3[[#This Row],[Deposito]],'SAPROV (2)'!D:E,2,FALSE) -> A01 | K20: COMISIONES BANCARIAS | L20: =VLOOKUP(Tabla3[[#This Row],[PROVEEDOR]],'SAPROV (2)'!A:B,2,FALSE) -> 04 | M20: =VLOOKUP(Tabla3[[#This Row],[SERVICIO]],'SAPROV (2)'!I:J,2,FALSE) -> SERV0060 | N20: ?COMISIONES BANCARIAS | P20: =VLOOKUP(Tabla3[[#This Row],[FECHA]],TASA[],2,FALSE) -> 330.38 | Q20: =D20/P20 -> -8.3518675 | R20: BANESCO
A21: 46035 | B21: 13267244404 | C21: COM. TRF. CR.INM.OB | D21: -3000 | E21: D | F21: =VLOOKUP(Tabla3[[#This Row],[CONTABLE]],'SAPROV (2)'!L:M,2,FALSE) -> #N/A | H21: ADMINISTRATIVOS | I21: =VLOOKUP(Tabla3[[#This Row],[Deposito]],'SAPROV (2)'!D:E,2,FALSE) -> A01 | K21: COMISIONES BANCARIAS | L21: =VLOOKUP(Tabla3[[#This Row],[PROVEEDOR]],'SAPROV (2)'!A:B,2,FALSE) -> 04 | M21: =VLOOKUP(Tabla3[[#This Row],[SERVICIO]],'SAPROV (2)'!I:J,2,FALSE) -> SERV0060 | N21: ?COMISIONES BANCARIAS | P21: =VLOOKUP(Tabla3[[#This Row],[FECHA]],TASA[],2,FALSE) -> 330.38 | Q21: =D21/P21 -> -9.0804528 | R21: BANESCO
A22: 46035 | B22: 13267396284 | C22: COM. TRF. CR.INM.OB | D22: -371.67 | E22: D | F22: =VLOOKUP(Tabla3[[#This Row],[CONTABLE]],'SAPROV (2)'!L:M,2,FALSE) -> #N/A | H22: ADMINISTRATIVOS | I22: =VLOOKUP(Tabla3[[#This Row],[Deposito]],'SAPROV (2)'!D:E,2,FALSE) -> A01 | K22: COMISIONES BANCARIAS | L22: =VLOOKUP(Tabla3[[#This Row],[PROVEEDOR]],'SAPROV (2)'!A:B,2,FALSE) -> 04 | M22: =VLOOKUP(Tabla3[[#This Row],[SERVICIO]],'SAPROV (2)'!I:J,2,FALSE) -> SERV0060 | N22: ?COMISIONES BANCARIAS | P22: =VLOOKUP(Tabla3[[#This Row],[FECHA]],TASA[],2,FALSE) -> 330.38 | Q22: =D22/P22 -> -1.1249773 | R22: BANESCO
... A138: 46042 | B138: 105405571 | C138: MANT AFIL CANAL VIRT DIC25 | D138: -450.92 | E138: D | F138: =VLOOKUP(Tabla3[[#This Row],[CONTABLE]],'SAPROV (2)'!L:M,2,FALSE) -> #N/A | H138: ADMINISTRATIVOS | I138: =VLOOKUP(Tabla3[[#This Row],[Deposito]],'SAPROV (2)'!D:E,2,FALSE) -> A01 | K138: COMISIONES BANCARIAS | L138: =VLOOKUP(Tabla3[[#This Row],[PROVEEDOR]],'SAPROV (2)'!A:B,2,FALSE) -> 04 | M138: =VLOOKUP(Tabla3[[#This Row],[SERVICIO]],'SAPROV (2)'!I:J,2,FALSE) -> SERV0060 | N138: ?COMISIONES BANCARIAS | P138: =VLOOKUP(Tabla3[[#This Row],[FECHA]],TASA[],2,FALSE) -> 344.51 | Q138: =D138/P138 -> -1.3088735 | R138: BDT
A139: 46052 | C139: CARGO EMISION EDO DE CUENTA | D139: -30 | E139: D | F139: =VLOOKUP(Tabla3[[#This Row],[CONTABLE]],'SAPROV (2)'!L:M,2,FALSE) -> #N/A | H139: ADMINISTRATIVOS | I139: =VLOOKUP(Tabla3[[#This Row],[Deposito]],'SAPROV (2)'!D:E,2,FALSE) -> A01 | K139: COMISIONES BANCARIAS | L139: =VLOOKUP(Tabla3[[#This Row],[PROVEEDOR]],'SAPROV (2)'!A:B,2,FALSE) -> 04 | M139: =VLOOKUP(Tabla3[[#This Row],[SERVICIO]],'SAPROV (2)'!I:J,2,FALSE) -> SERV0060 | N139: ?COMISIONES BANCARIAS | P139: =VLOOKUP(Tabla3[[#This Row],[FECHA]],TASA[],2,FALSE) -> 367.31 | Q139: =D139/P139 -> -0.08167488 | R139: BDT
A140: 46052 | C140: CARGO POR SERVICIO | D140: -20 | E140: D | F140: =VLOOKUP(Tabla3[[#This Row],[CONTABLE]],'SAPROV (2)'!L:M,2,FALSE) -> #N/A | H140: ADMINISTRATIVOS | I140: =VLOOKUP(Tabla3[[#This Row],[Deposito]],'SAPROV (2)'!D:E,2,FALSE) -> A01 | K140: COMISIONES BANCARIAS | L140: =VLOOKUP(Tabla3[[#This Row],[PROVEEDOR]],'SAPROV (2)'!A:B,2,FALSE) -> 04 | M140: =VLOOKUP(Tabla3[[#This Row],[SERVICIO]],'SAPROV (2)'!I:J,2,FALSE) -> SERV0060 | N140: ?COMISIONES BANCARIAS | P140: =VLOOKUP(Tabla3[[#This Row],[FECHA]],TASA[],2,FALSE) -> 367.31 | Q140: =D140/P140 -> -0.05444992 | R140: BDT
A141: 46027 | B141: 43700024375 | C141: OP.CRED.DIRT.CLTE-CLTE PJ JURIDICA ELECTRON | D141: -10.1 | E141: D | F141: =VLOOKUP(Tabla3[[#This Row],[CONTABLE]],'SAPROV (2)'!L:M,2,FALSE) -> #N/A | H141: ADMINISTRATIVOS | I141: =VLOOKUP(Tabla3[[#This Row],[Deposito]],'SAPROV (2)'!D:E,2,FALSE) -> A01 | K141: COMISIONES BANCARIAS | L141: =VLOOKUP(Tabla3[[#This Row],[PROVEEDOR]],'SAPROV (2)'!A:B,2,FALSE) -> 04 | M141: =VLOOKUP(Tabla3[[#This Row],[SERVICIO]],'SAPROV (2)'!I:J,2,FALSE) -> SERV0060 | N141: ?COMISIONES BANCARIAS | P141: =VLOOKUP(Tabla3[[#This Row],[FECHA]],TASA[],2,FALSE) -> 304.68 | Q141: =D141/P141 -> -0.033149534 | R141: MERCANTIL
A142: 46042 | B142: 43700031193 | C142: OP.CRED.DIRT. CLTE-CLTE PJ ELECTRON | D142: -10.1 | E142: D | F142: =VLOOKUP(Tabla3[[#This Row],[CONTABLE]],'SAPROV (2)'!L:M,2,FALSE) -> #N/A | H142: ADMINISTRATIVOS | I142: =VLOOKUP(Tabla3[[#This Row],[Deposito]],'SAPROV (2)'!D:E,2,FALSE) -> A01 | K142: COMISIONES BANCARIAS | L142: =VLOOKUP(Tabla3[[#This Row],[PROVEEDOR]],'SAPROV (2)'!A:B,2,FALSE) -> 04 | M142: =VLOOKUP(Tabla3[[#This Row],[SERVICIO]],'SAPROV (2)'!I:J,2,FALSE) -> SERV0060 | N142: ?COMISIONES BANCARIAS | P142: =VLOOKUP(Tabla3[[#This Row],[FECHA]],TASA[],2,FALSE) -> 344.51 | Q142: =D142/P142 -> -0.029317001 | R142: MERCANTIL
A143: 46049 | B143: 10781498729 | C143: COMISION POR TRANSFERENCIA DE FONDOS | D143: -3000 | E143: D | F143: =VLOOKUP(Tabla3[[#This Row],[CONTABLE]],'SAPROV (2)'!L:M,2,FALSE) -> #N/A | H143: ADMINISTRATIVOS | I143: =VLOOKUP(Tabla3[[#This Row],[Deposito]],'SAPROV (2)'!D:E,2,FALSE) -> A01 | K143: COMISIONES BANCARIAS | L143: =VLOOKUP(Tabla3[[#This Row],[PROVEEDOR]],'SAPROV (2)'!A:B,2,FALSE) -> 04 | M143: =VLOOKUP(Tabla3[[#This Row],[SERVICIO]],'SAPROV (2)'!I:J,2,FALSE) -> SERV0060 | N143: ?COMISIONES BANCARIAS | P143: =VLOOKUP(Tabla3[[#This Row],[FECHA]],TASA[],2,FALSE) -> 358.92 | Q143: =D143/P143 -> -8.3584086 | R143: MERCANTIL
A144: 46049 | B144: 10781498469 | C144: COMISION POR TRANSFERENCIA DE FONDOS | D144: -3000 | E144: D | F144: =VLOOKUP(Tabla3[[#This Row],[CONTABLE]],'SAPROV (2)'!L:M,2,FALSE) -> #N/A | H144: ADMINISTRATIVOS | I144: =VLOOKUP(Tabla3[[#This Row],[Deposito]],'SAPROV (2)'!D:E,2,FALSE) -> A01 | K144: COMISIONES BANCARIAS | L144: =VLOOKUP(Tabla3[[#This Row],[PROVEEDOR]],'SAPROV (2)'!A:B,2,FALSE) -> 04 | M144: =VLOOKUP(Tabla3[[#This Row],[SERVICIO]],'SAPROV (2)'!I:J,2,FALSE) -> SERV0060 | N144: ?COMISIONES BANCARIAS | P144: =VLOOKUP(Tabla3[[#This Row],[FECHA]],TASA[],2,FALSE) -> 358.92 | Q144: =D144/P144 -> -8.3584086 | R144: MERCANTIL
A145: 46049 | B145: 10781498160 | C145: COMISION POR TRANSFERENCIA DE FONDOS | D145: -3000 | E145: D | F145: =VLOOKUP(Tabla3[[#This Row],[CONTABLE]],'SAPROV (2)'!L:M,2,FALSE) -> #N/A | H145: ADMINISTRATIVOS | I145: =VLOOKUP(Tabla3[[#This Row],[Deposito]],'SAPROV (2)'!D:E,2,FALSE) -> A01 | K145: COMISIONES BANCARIAS | L145: =VLOOKUP(Tabla3[[#This Row],[PROVEEDOR]],'SAPROV (2)'!A:B,2,FALSE) -> 04 | M145: =VLOOKUP(Tabla3[[#This Row],[SERVICIO]],'SAPROV (2)'!I:J,2,FALSE) -> SERV0060 | N145: ?COMISIONES BANCARIAS | P145: =VLOOKUP(Tabla3[[#This Row],[FECHA]],TASA[],2,FALSE) -> 358.92 | Q145: =D145/P145 -> -8.3584086 | R145: MERCANTIL
A146: 46049 | B146: 10781497975 | C146: COMISION POR TRANSFERENCIA DE FONDOS | D146: -3000 | E146: D | F146: =VLOOKUP(Tabla3[[#This Row],[CONTABLE]],'SAPROV (2)'!L:M,2,FALSE) -> #N/A | H146: ADMINISTRATIVOS | I146: =VLOOKUP(Tabla3[[#This Row],[Deposito]],'SAPROV (2)'!D:E,2,FALSE) -> A01 | K146: COMISIONES BANCARIAS | L146: =VLOOKUP(Tabla3[[#This Row],[PROVEEDOR]],'SAPROV (2)'!A:B,2,FALSE) -> 04 | M146: =VLOOKUP(Tabla3[[#This Row],[SERVICIO]],'SAPROV (2)'!I:J,2,FALSE) -> SERV0060 | N146: ?COMISIONES BANCARIAS | P146: =VLOOKUP(Tabla3[[#This Row],[FECHA]],TASA[],2,FALSE) -> 358.92 | Q146: =D146/P146 -> -8.3584086 | R146: MERCANTIL
A147: 46049 | B147: 10781497710 | C147: COMISION POR TRANSFERENCIA DE FONDOS | D147: -3000 | E147: D | F147: =VLOOKUP(Tabla3[[#This Row],[CONTABLE]],'SAPROV (2)'!L:M,2,FALSE) -> #N/A | H147: ADMINISTRATIVOS | I147: =VLOOKUP(Tabla3[[#This Row],[Deposito]],'SAPROV (2)'!D:E,2,FALSE) -> A01 | K147: COMISIONES BANCARIAS | L147: =VLOOKUP(Tabla3[[#This Row],[PROVEEDOR]],'SAPROV (2)'!A:B,2,FALSE) -> 04 | M147: =VLOOKUP(Tabla3[[#This Row],[SERVICIO]],'SAPROV (2)'!I:J,2,FALSE) -> SERV0060 | N147: ?COMISIONES BANCARIAS | P147: =VLOOKUP(Tabla3[[#This Row],[FECHA]],TASA[],2,FALSE) -> 358.92 | Q147: =D147/P147 -> -8.3584086 | R147: MERCANTIL
A148: 46049 | B148: 10781497448 | C148: COMISION POR TRANSFERENCIA DE FONDOS | D148: -3000 | E148: D | F148: =VLOOKUP(Tabla3[[#This Row],[CONTABLE]],'SAPROV (2)'!L:M,2,FALSE) -> #N/A | H148: ADMINISTRATIVOS | I148: =VLOOKUP(Tabla3[[#This Row],[Deposito]],'SAPROV (2)'!D:E,2,FALSE) -> A01 | K148: COMISIONES BANCARIAS | L148: =VLOOKUP(Tabla3[[#This Row],[PROVEEDOR]],'SAPROV (2)'!A:B,2,FALSE) -> 04 | M148: =VLOOKUP(Tabla3[[#This Row],[SERVICIO]],'SAPROV (2)'!I:J,2,FALSE) -> SERV0060 | N148: ?COMISIONES BANCARIAS | P148: =VLOOKUP(Tabla3[[#This Row],[FECHA]],TASA[],2,FALSE) -> 358.92 | Q148: =D148/P148 -> -8.3584086 | R148: MERCANTIL
A149: 46049 | B149: 10781497178 | C149: COMISION POR TRANSFERENCIA DE FONDOS | D149: -3000 | E149: D | F149: =VLOOKUP(Tabla3[[#This Row],[CONTABLE]],'SAPROV (2)'!L:M,2,FALSE) -> #N/A | H149: ADMINISTRATIVOS | I149: =VLOOKUP(Tabla3[[#This Row],[Deposito]],'SAPROV (2)'!D:E,2,FALSE) -> A01 | K149: COMISIONES BANCARIAS | L149: =VLOOKUP(Tabla3[[#This Row],[PROVEEDOR]],'SAPROV (2)'!A:B,2,FALSE) -> 04 | M149: =VLOOKUP(Tabla3[[#This Row],[SERVICIO]],'SAPROV (2)'!I:J,2,FALSE) -> SERV0060 | N149: ?COMISIONES BANCARIAS | P149: =VLOOKUP(Tabla3[[#This Row],[FECHA]],TASA[],2,FALSE) -> 358.92 | Q149: =D149/P149 -> -8.3584086 | R149: MERCANTIL
A150: 46049 | B150: 43700028344 | C150: OP.CRED.DIRT.CLTE-CLTE PJ JURIDICA ELECTRON | D150: -10.1 | E150: D | F150: =VLOOKUP(Tabla3[[#This Row],[CONTABLE]],'SAPROV (2)'!L:M,2,FALSE) -> #N/A | H150: ADMINISTRATIVOS | I150: =VLOOKUP(Tabla3[[#This Row],[Deposito]],'SAPROV (2)'!D:E,2,FALSE) -> A01 | K150: COMISIONES BANCARIAS | L150: =VLOOKUP(Tabla3[[#This Row],[PROVEEDOR]],'SAPROV (2)'!A:B,2,FALSE) -> 04 | M150: =VLOOKUP(Tabla3[[#This Row],[SERVICIO]],'SAPROV (2)'!I:J,2,FALSE) -> SERV0060 | N150: ?COMISIONES BANCARIAS | P150: =VLOOKUP(Tabla3[[#This Row],[FECHA]],TASA[],2,FALSE) -> 358.92 | Q150: =D150/P150 -> -0.028139975 | R150: MERCANTIL
A151: 46052 | B151: 71600000000 | C151: EMISION EDO. DEC TA.MONEDA NAC. EXT. | D151: -8 | E151: D | F151: =VLOOKUP(Tabla3[[#This Row],[CONTABLE]],'SAPROV (2)'!L:M,2,FALSE) -> #N/A | H151: ADMINISTRATIVOS | I151: =VLOOKUP(Tabla3[[#This Row],[Deposito]],'SAPROV (2)'!D:E,2,FALSE) -> A01 | K151: COMISIONES BANCARIAS | L151: =VLOOKUP(Tabla3[[#This Row],[PROVEEDOR]],'SAPROV (2)'!A:B,2,FALSE) -> 04 | M151: =VLOOKUP(Tabla3[[#This Row],[SERVICIO]],'SAPROV (2)'!I:J,2,FALSE) -> SERV0060 | N151: ?COMISIONES BANCARIAS | P151: =VLOOKUP(Tabla3[[#This Row],[FECHA]],TASA[],2,FALSE) -> 367.31 | Q151: =D151/P151 -> -0.021779968 | R151: MERCANTIL
A152: 46052 | B152: 91577700000 | C152: TARIFA MANTENIMIENTO DE CUENTA | D152: -8 | E152: D | F152: =VLOOKUP(Tabla3[[#This Row],[CONTABLE]],'SAPROV (2)'!L:M,2,FALSE) -> #N/A | H152: ADMINISTRATIVOS | I152: =VLOOKUP(Tabla3[[#This Row],[Deposito]],'SAPROV (2)'!D:E,2,FALSE) -> A01 | K152: COMISIONES BANCARIAS | L152: =VLOOKUP(Tabla3[[#This Row],[PROVEEDOR]],'SAPROV (2)'!A:B,2,FALSE) -> 04 | M152: =VLOOKUP(Tabla3[[#This Row],[SERVICIO]],'SAPROV (2)'!I:J,2,FALSE) -> SERV0060 | N152: ?COMISIONES BANCARIAS | P152: =VLOOKUP(Tabla3[[#This Row],[FECHA]],TASA[],2,FALSE) -> 367.31 | Q152: =D152/P152 -> -0.021779968 | R152: MERCANTIL
... A178: 46027 | B178: 5926 | C178: RECARGA DE 120 LITROS DE COMBUSTIBLE PERSONAL DEL SESAY | D178: -18282 | E178: D | F178: =VLOOKUP(Tabla3[[#This Row],[CONTABLE]],'SAPROV (2)'!L:M,2,FALSE) -> #N/A | H178: Pira café | I178: =VLOOKUP(Tabla3[[#This Row],[Deposito]],'SAPROV (2)'!D:E,2,FALSE) -> 02 | K178: COMBUSTIBLE | L178: =VLOOKUP(Tabla3[[#This Row],[PROVEEDOR]],'SAPROV (2)'!A:B,2,FALSE) -> 12 | M178: =VLOOKUP(Tabla3[[#This Row],[SERVICIO]],'SAPROV (2)'!I:J,2,FALSE) -> SERV0038 | N178: ?GASTOS COMBUSTIBLE/ GASOLINA | P178: =VLOOKUP(Tabla3[[#This Row],[FECHA]],TASA[],2,FALSE) -> 304.68 | Q178: =D178/P178 -> -60.003939 | R178: CAJA CHICA
A179: 46027 | C179: RECARGA DE 40 LITROS DE COMBUSTIBLE PERSONAL DEL SESAY | D179: -6509 | E179: D | F179: =VLOOKUP(Tabla3[[#This Row],[CONTABLE]],'SAPROV (2)'!L:M,2,FALSE) -> #N/A | H179: Pira café | I179: =VLOOKUP(Tabla3[[#This Row],[Deposito]],'SAPROV (2)'!D:E,2,FALSE) -> 02 | K179: COMBUSTIBLE | L179: =VLOOKUP(Tabla3[[#This Row],[PROVEEDOR]],'SAPROV (2)'!A:B,2,FALSE) -> 12 | M179: =VLOOKUP(Tabla3[[#This Row],[SERVICIO]],'SAPROV (2)'!I:J,2,FALSE) -> SERV0038 | N179: ?GASTOS COMBUSTIBLE/ GASOLINA | P179: =VLOOKUP(Tabla3[[#This Row],[FECHA]],TASA[],2,FALSE) -> 304.68 | Q179: =D179/P179 -> -21.363398 | R179: CAJA CHICA
A180: 46027 | B180: 2142 | C180: RECARGA DE 20 LITROS DE COMBUSTIBLE JOSE PINEDA | D180: -3046.8 | E180: D | F180: =VLOOKUP(Tabla3[[#This Row],[CONTABLE]],'SAPROV (2)'!L:M,2,FALSE) -> #N/A | H180: Productor Agro tendencias | I180: =VLOOKUP(Tabla3[[#This Row],[Deposito]],'SAPROV (2)'!D:E,2,FALSE) -> 07 | K180: COMBUSTIBLE | L180: =VLOOKUP(Tabla3[[#This Row],[PROVEEDOR]],'SAPROV (2)'!A:B,2,FALSE) -> 12 | M180: =VLOOKUP(Tabla3[[#This Row],[SERVICIO]],'SAPROV (2)'!I:J,2,FALSE) -> SERV0038 | N180: ?GASTOS COMBUSTIBLE/ GASOLINA | P180: =VLOOKUP(Tabla3[[#This Row],[FECHA]],TASA[],2,FALSE) -> 304.68 | Q180: =D180/P180 -> -10 | R180: CAJA CHICA
A181: 46027 | B181: 1040 | C181: MES DE ENERO AGRO TENDENCIA, C.A. | D181: -3616.44 | E181: D | F181: =VLOOKUP(Tabla3[[#This Row],[CONTABLE]],'SAPROV (2)'!L:M,2,FALSE) -> #N/A | H181: ADMINISTRATIVOS | I181: =VLOOKUP(Tabla3[[#This Row],[Deposito]],'SAPROV (2)'!D:E,2,FALSE) -> A01 | K181: SUNAGRO | L181: =VLOOKUP(Tabla3[[#This Row],[PROVEEDOR]],'SAPROV (2)'!A:B,2,FALSE) -> 10 | M181: =VLOOKUP(Tabla3[[#This Row],[SERVICIO]],'SAPROV (2)'!I:J,2,FALSE) -> SERV0145 | N181: GASTOS DE GUIA DE TRASLADO | P181: =VLOOKUP(Tabla3[[#This Row],[FECHA]],TASA[],2,FALSE) -> 304.68 | Q181: =D181/P181 -> -11.869634 | R181: CAJA CHICA
A182: 46028 | B182: 6876 | C182: RECARGA DE 10 LITROS DE GASOLINA MOTO ASIGNADA A DOMINGO DOMINGUEZ | D182: -1525 | E182: D | F182: =VLOOKUP(Tabla3[[#This Row],[CONTABLE]],'SAPROV (2)'!L:M,2,FALSE) -> #N/A | H182: Productor Agro tendencias | I182: =VLOOKUP(Tabla3[[#This Row],[Deposito]],'SAPROV (2)'!D:E,2,FALSE) -> 07 | K182: COMBUSTIBLE | L182: =VLOOKUP(Tabla3[[#This Row],[PROVEEDOR]],'SAPROV (2)'!A:B,2,FALSE) -> 12 | M182: =VLOOKUP(Tabla3[[#This Row],[SERVICIO]],'SAPROV (2)'!I:J,2,FALSE) -> SERV0038 | N182: ?GASTOS COMBUSTIBLE/ GASOLINA | P182: =VLOOKUP(Tabla3[[#This Row],[FECHA]],TASA[],2,FALSE) -> 308.15 | Q182: =D182/P182 -> -4.9488885 | R182: CAJA CHICA
A183: 46028 | B183: 3975 | C183: RECARGA DE 58 LITROS DE GASOLINA CAMIONETA LK 153 | D183: -8936.64 | E183: D | F183: =VLOOKUP(Tabla3[[#This Row],[CONTABLE]],'SAPROV (2)'!L:M,2,FALSE) -> #N/A | H183: ADMINISTRATIVOS | I183: =VLOOKUP(Tabla3[[#This Row],[Deposito]],'SAPROV (2)'!D:E,2,FALSE) -> A01 | K183: COMBUSTIBLE | L183: =VLOOKUP(Tabla3[[#This Row],[PROVEEDOR]],'SAPROV (2)'!A:B,2,FALSE) -> 12 | M183: =VLOOKUP(Tabla3[[#This Row],[SERVICIO]],'SAPROV (2)'!I:J,2,FALSE) -> SERV0038 | N183: ?GASTOS COMBUSTIBLE/ GASOLINA | P183: =VLOOKUP(Tabla3[[#This Row],[FECHA]],TASA[],2,FALSE) -> 308.15 | Q183: =D183/P183 -> -29.000941 | R183: CAJA CHICA
A184: 46028 | B184: 7394 | C184: RECARGA DE 70 LITROS DE GASOLINA CAMION BLANCO (OSCAR) | D184: -10785.6 | E184: D | F184: =VLOOKUP(Tabla3[[#This Row],[CONTABLE]],'SAPROV (2)'!L:M,2,FALSE) -> #N/A | H184: Productor Agro tendencias | I184: =VLOOKUP(Tabla3[[#This Row],[Deposito]],'SAPROV (2)'!D:E,2,FALSE) -> 07 | K184: COMBUSTIBLE | L184: =VLOOKUP(Tabla3[[#This Row],[PROVEEDOR]],'SAPROV (2)'!A:B,2,FALSE) -> 12 | M184: =VLOOKUP(Tabla3[[#This Row],[SERVICIO]],'SAPROV (2)'!I:J,2,FALSE) -> SERV0038 | N184: ?GASTOS COMBUSTIBLE/ GASOLINA | P184: =VLOOKUP(Tabla3[[#This Row],[FECHA]],TASA[],2,FALSE) -> 308.15 | Q184: =D184/P184 -> -35.001136 | R184: CAJA CHICA
A185: 46029 | B185: 152 | C185: RECARGA 10 LITROS DE GASOLINA MOTO ASIGNADA A JAVIER CHIRINO | D185: -1560 | E185: D | F185: =VLOOKUP(Tabla3[[#This Row],[CONTABLE]],'SAPROV (2)'!L:M,2,FALSE) -> #N/A | H185: Pira café | I185: =VLOOKUP(Tabla3[[#This Row],[Deposito]],'SAPROV (2)'!D:E,2,FALSE) -> 02 | K185: COMBUSTIBLE | L185: =VLOOKUP(Tabla3[[#This Row],[PROVEEDOR]],'SAPROV (2)'!A:B,2,FALSE) -> 12 | M185: =VLOOKUP(Tabla3[[#This Row],[SERVICIO]],'SAPROV (2)'!I:J,2,FALSE) -> SERV0038 | N185: ?GASTOS COMBUSTIBLE/ GASOLINA | P185: =VLOOKUP(Tabla3[[#This Row],[FECHA]],TASA[],2,FALSE) -> 311.88 | Q185: =D185/P185 -> -5.0019238 | R185: CAJA CHICA
A186: 46029 | B186: 5146 | C186: RECARGA DE 9 LITROS DE GASOLINA MOTO ASIGNADA A EUCARYS RODRIGUEZ | D186: -1457 | E186: D | F186: =VLOOKUP(Tabla3[[#This Row],[CONTABLE]],'SAPROV (2)'!L:M,2,FALSE) -> #N/A | H186: Pira café | I186: =VLOOKUP(Tabla3[[#This Row],[Deposito]],'SAPROV (2)'!D:E,2,FALSE) -> 02 | K186: COMBUSTIBLE | L186: =VLOOKUP(Tabla3[[#This Row],[PROVEEDOR]],'SAPROV (2)'!A:B,2,FALSE) -> 12 | M186: =VLOOKUP(Tabla3[[#This Row],[SERVICIO]],'SAPROV (2)'!I:J,2,FALSE) -> SERV0038 | N186: ?GASTOS COMBUSTIBLE/ GASOLINA | P186: =VLOOKUP(Tabla3[[#This Row],[FECHA]],TASA[],2,FALSE) -> 311.88 | Q186: =D186/P186 -> -4.6716686 | R186: CAJA CHICA
A187: 46029 | B187: 6251 | C187: RECARGA DE 140 LITROS DE GASOLINA PARA EL TRITON ROJO | D187: -21833 | E187: D | F187: =VLOOKUP(Tabla3[[#This Row],[CONTABLE]],'SAPROV (2)'!L:M,2,FALSE) -> #N/A | H187: Productor Agro tendencias | I187: =VLOOKUP(Tabla3[[#This Row],[Deposito]],'SAPROV (2)'!D:E,2,FALSE) -> 07 | K187: COMBUSTIBLE | L187: =VLOOKUP(Tabla3[[#This Row],[PROVEEDOR]],'SAPROV (2)'!A:B,2,FALSE) -> 12 | M187: =VLOOKUP(Tabla3[[#This Row],[SERVICIO]],'SAPROV (2)'!I:J,2,FALSE) -> SERV0038 | N187: ?GASTOS COMBUSTIBLE/ GASOLINA | P187: =VLOOKUP(Tabla3[[#This Row],[FECHA]],TASA[],2,FALSE) -> 311.88 | Q187: =D187/P187 -> -70.004489 | R187: CAJA CHICA
A188: 46029 | B188: 6396 | C188: RECARGA DE 40 LITROS DE COMBUSTIBLE PARA TOYOTA HEMBRITA | D188: -6238 | E188: D | F188: =VLOOKUP(Tabla3[[#This Row],[CONTABLE]],'SAPROV (2)'!L:M,2,FALSE) -> #N/A | H188: Pira café | I188: =VLOOKUP(Tabla3[[#This Row],[Deposito]],'SAPROV (2)'!D:E,2,FALSE) -> 02 | K188: COMBUSTIBLE | L188: =VLOOKUP(Tabla3[[#This Row],[PROVEEDOR]],'SAPROV (2)'!A:B,2,FALSE) -> 12 | M188: =VLOOKUP(Tabla3[[#This Row],[SERVICIO]],'SAPROV (2)'!I:J,2,FALSE) -> SERV0038 | N188: ?GASTOS COMBUSTIBLE/ GASOLINA | P188: =VLOOKUP(Tabla3[[#This Row],[FECHA]],TASA[],2,FALSE) -> 311.88 | Q188: =D188/P188 -> -20.001283 | R188: CAJA CHICA
A189: 46029 | B189: 6921 | C189: RECARGA DE 10 LITROS DE GASOLINA TECNICO CARLOS PUERTA | D189: -1560 | E189: D | F189: =VLOOKUP(Tabla3[[#This Row],[CONTABLE]],'SAPROV (2)'!L:M,2,FALSE) -> #N/A | H189: Pira café | I189: =VLOOKUP(Tabla3[[#This Row],[Deposito]],'SAPROV (2)'!D:E,2,FALSE) -> 02 | K189: COMBUSTIBLE | L189: =VLOOKUP(Tabla3[[#This Row],[PROVEEDOR]],'SAPROV (2)'!A:B,2,FALSE) -> 12 | M189: =VLOOKUP(Tabla3[[#This Row],[SERVICIO]],'SAPROV (2)'!I:J,2,FALSE) -> SERV0038 | N189: ?GASTOS COMBUSTIBLE/ GASOLINA | P189: =VLOOKUP(Tabla3[[#This Row],[FECHA]],TASA[],2,FALSE) -> 311.88 | Q189: =D189/P189 -> -5.0019238 | R189: CAJA CHICA
A190: 46029 | B190: 7291 | C190: RECARGA DE 20 LITROS DE GASOLINA PARA MOTO ASIGNADA A LOS TECNICOS HENRY Y CESAR PETIT | D190: -3119 | E190: D | F190: =VLOOKUP(Tabla3[[#This Row],[CONTABLE]],'SAPROV (2)'!L:M,2,FALSE) -> #N/A | H190: Pira café | I190: =VLOOKUP(Tabla3[[#This Row],[Deposito]],'SAPROV (2)'!D:E,2,FALSE) -> 02 | K190: COMBUSTIBLE | L190: =VLOOKUP(Tabla3[[#This Row],[PROVEEDOR]],'SAPROV (2)'!A:B,2,FALSE) -> 12 | M190: =VLOOKUP(Tabla3[[#This Row],[SERVICIO]],'SAPROV (2)'!I:J,2,FALSE) -> SERV0038 | N190: ?GASTOS COMBUSTIBLE/ GASOLINA | P190: =VLOOKUP(Tabla3[[#This Row],[FECHA]],TASA[],2,FALSE) -> 311.88 | Q190: =D190/P190 -> -10.000641 | R190: CAJA CHICA
A191: 46029 | B191: 7693 | C191: RECARGA DE 10 LITROS DE GASOLINA TECNICO LUINEIBER ALVARADO | D191: -1560 | E191: D | F191: =VLOOKUP(Tabla3[[#This Row],[CONTABLE]],'SAPROV (2)'!L:M,2,FALSE) -> #N/A | H191: Pira café | I191: =VLOOKUP(Tabla3[[#This Row],[Deposito]],'SAPROV (2)'!D:E,2,FALSE) -> 02 | K191: COMBUSTIBLE | L191: =VLOOKUP(Tabla3[[#This Row],[PROVEEDOR]],'SAPROV (2)'!A:B,2,FALSE) -> 12 | M191: =VLOOKUP(Tabla3[[#This Row],[SERVICIO]],'SAPROV (2)'!I:J,2,FALSE) -> SERV0038 | N191: ?GASTOS COMBUSTIBLE/ GASOLINA | P191: =VLOOKUP(Tabla3[[#This Row],[FECHA]],TASA[],2,FALSE) -> 311.88 | Q191: =D191/P191 -> -5.0019238 | R191: CAJA CHICA
... A195: 46030 | B195: 2023 | C195: RECARGA DE 50 LITROS DE GASOLINA CAMIONETA LK 153 | D195: -8026 | E195: D | F195: =VLOOKUP(Tabla3[[#This Row],[CONTABLE]],'SAPROV (2)'!L:M,2,FALSE) -> #N/A | H195: ADMINISTRATIVOS | I195: =VLOOKUP(Tabla3[[#This Row],[Deposito]],'SAPROV (2)'!D:E,2,FALSE) -> A01 | K195: COMBUSTIBLE | L195: =VLOOKUP(Tabla3[[#This Row],[PROVEEDOR]],'SAPROV (2)'!A:B,2,FALSE) -> 12 | M195: =VLOOKUP(Tabla3[[#This Row],[SERVICIO]],'SAPROV (2)'!I:J,2,FALSE) -> SERV0038 | N195: ?GASTOS COMBUSTIBLE/ GASOLINA | P195: =VLOOKUP(Tabla3[[#This Row],[FECHA]],TASA[],2,FALSE) -> 321.03 | Q195: =D195/P195 -> -25.000779 | R195: CAJA CHICA
A196: 46030 | C196: PAGO DE ESTACIONAMIENT CAMIONETA LK 153 | D196: -311.5 | E196: D | F196: =VLOOKUP(Tabla3[[#This Row],[CONTABLE]],'SAPROV (2)'!L:M,2,FALSE) -> #N/A | H196: ADMINISTRATIVOS | I196: =VLOOKUP(Tabla3[[#This Row],[Deposito]],'SAPROV (2)'!D:E,2,FALSE) -> A01 | K196: VEHICULOS | L196: =VLOOKUP(Tabla3[[#This Row],[PROVEEDOR]],'SAPROV (2)'!A:B,2,FALSE) -> 17 | M196: =VLOOKUP(Tabla3[[#This Row],[SERVICIO]],'SAPROV (2)'!I:J,2,FALSE) -> SERV0025 | N196: ?GASTOS VEHICULOS | P196: =VLOOKUP(Tabla3[[#This Row],[FECHA]],TASA[],2,FALSE) -> 321.03 | Q196: =D196/P196 -> -0.9703143 | R196: CAJA CHICA
A197: 46031 | B197: 576 | C197: RECARGA DE GASOLINA A TOYOTA HEMBRITA CAFE | D197: -6509 | E197: D | F197: =VLOOKUP(Tabla3[[#This Row],[CONTABLE]],'SAPROV (2)'!L:M,2,FALSE) -> #N/A | H197: Pira café | I197: =VLOOKUP(Tabla3[[#This Row],[Deposito]],'SAPROV (2)'!D:E,2,FALSE) -> 02 | K197: COMBUSTIBLE | L197: =VLOOKUP(Tabla3[[#This Row],[PROVEEDOR]],'SAPROV (2)'!A:B,2,FALSE) -> 12 | M197: =VLOOKUP(Tabla3[[#This Row],[SERVICIO]],'SAPROV (2)'!I:J,2,FALSE) -> SERV0038 | N197: ?GASTOS COMBUSTIBLE/ GASOLINA | P197: =VLOOKUP(Tabla3[[#This Row],[FECHA]],TASA[],2,FALSE) -> 325.39 | Q197: =D197/P197 -> -20.003688 | R197: CAJA CHICA
A198: 46034 | B198: 599 | C198: RECARGA DE 40 LITROS DE GASOLINA A TOYOTA HEMBRITA CAFE | D198: -6608 | E198: D | F198: =VLOOKUP(Tabla3[[#This Row],[CONTABLE]],'SAPROV (2)'!L:M,2,FALSE) -> #N/A | H198: Pira café | I198: =VLOOKUP(Tabla3[[#This Row],[Deposito]],'SAPROV (2)'!D:E,2,FALSE) -> 02 | K198: COMBUSTIBLE | L198: =VLOOKUP(Tabla3[[#This Row],[PROVEEDOR]],'SAPROV (2)'!A:B,2,FALSE) -> 12 | M198: =VLOOKUP(Tabla3[[#This Row],[SERVICIO]],'SAPROV (2)'!I:J,2,FALSE) -> SERV0038 | N198: ?GASTOS COMBUSTIBLE/ GASOLINA | P198: =VLOOKUP(Tabla3[[#This Row],[FECHA]],TASA[],2,FALSE) -> 330.38 | Q198: =D198/P198 -> -20.001211 | R198: CAJA CHICA
A199: 46034 | B199: 421 | C199: RECARGA DE 70 LITROS DE GASOLINA CAMION BLANCO | D199: -11388.3 | E199: D | F199: =VLOOKUP(Tabla3[[#This Row],[CONTABLE]],'SAPROV (2)'!L:M,2,FALSE) -> #N/A | H199: Productor Agro tendencias | I199: =VLOOKUP(Tabla3[[#This Row],[Deposito]],'SAPROV (2)'!D:E,2,FALSE) -> 07 | K199: COMBUSTIBLE | L199: =VLOOKUP(Tabla3[[#This Row],[PROVEEDOR]],'SAPROV (2)'!A:B,2,FALSE) -> 12 | M199: =VLOOKUP(Tabla3[[#This Row],[SERVICIO]],'SAPROV (2)'!I:J,2,FALSE) -> SERV0038 | N199: ?GASTOS COMBUSTIBLE/ GASOLINA | P199: =VLOOKUP(Tabla3[[#This Row],[FECHA]],TASA[],2,FALSE) -> 330.38 | Q199: =D199/P199 -> -34.470307 | R199: CAJA CHICA
A200: 46034 | B200: 4069 | C200: RECARGA DE LITROS DE GASOLINA TECNICO CESAR PETIT | D200: -1652 | E200: D | F200: =VLOOKUP(Tabla3[[#This Row],[CONTABLE]],'SAPROV (2)'!L:M,2,FALSE) -> #N/A | H200: Pira café | I200: =VLOOKUP(Tabla3[[#This Row],[Deposito]],'SAPROV (2)'!D:E,2,FALSE) -> 02 | K200: COMBUSTIBLE | L200: =VLOOKUP(Tabla3[[#This Row],[PROVEEDOR]],'SAPROV (2)'!A:B,2,FALSE) -> 12 | M200: =VLOOKUP(Tabla3[[#This Row],[SERVICIO]],'SAPROV (2)'!I:J,2,FALSE) -> SERV0038 | N200: ?GASTOS COMBUSTIBLE/ GASOLINA | P200: =VLOOKUP(Tabla3[[#This Row],[FECHA]],TASA[],2,FALSE) -> 330.38 | Q200: =D200/P200 -> -5.0003027 | R200: CAJA CHICA
A201: 46034 | B201: 3706 | C201: RECARGA DE 146 LITROS DE COMBUSTIBLE PERSONAL DEL SESAY | D201: -24090 | E201: D | F201: =VLOOKUP(Tabla3[[#This Row],[CONTABLE]],'SAPROV (2)'!L:M,2,FALSE) -> #N/A | H201: Pira café | I201: =VLOOKUP(Tabla3[[#This Row],[Deposito]],'SAPROV (2)'!D:E,2,FALSE) -> 02 | K201: COMBUSTIBLE | L201: =VLOOKUP(Tabla3[[#This Row],[PROVEEDOR]],'SAPROV (2)'!A:B,2,FALSE) -> 12 | M201: =VLOOKUP(Tabla3[[#This Row],[SERVICIO]],'SAPROV (2)'!I:J,2,FALSE) -> SERV0038 | N201: ?GASTOS COMBUSTIBLE/ GASOLINA | P201: =VLOOKUP(Tabla3[[#This Row],[FECHA]],TASA[],2,FALSE) -> 330.38 | Q201: =D201/P201 -> -72.916036 | R201: CAJA CHICA
A202: 46034 | B202: 1961 | C202: RECARGA DE 100 LITROS DE COMBUSTIBLE TRITON ROJO (NELSON) | D202: -16269 | E202: D | F202: =VLOOKUP(Tabla3[[#This Row],[CONTABLE]],'SAPROV (2)'!L:M,2,FALSE) -> #N/A | H202: Productor Agro tendencias | I202: =VLOOKUP(Tabla3[[#This Row],[Deposito]],'SAPROV (2)'!D:E,2,FALSE) -> 07 | K202: COMBUSTIBLE | L202: =VLOOKUP(Tabla3[[#This Row],[PROVEEDOR]],'SAPROV (2)'!A:B,2,FALSE) -> 12 | M202: =VLOOKUP(Tabla3[[#This Row],[SERVICIO]],'SAPROV (2)'!I:J,2,FALSE) -> SERV0038 | N202: ?GASTOS COMBUSTIBLE/ GASOLINA | P202: =VLOOKUP(Tabla3[[#This Row],[FECHA]],TASA[],2,FALSE) -> 330.38 | Q202: =D202/P202 -> -49.243296 | R202: CAJA CHICA
A203: 46034 | B203: 4482 | C203: RECARGA DE 10 LITROS DE GASOLINA MOTO TALLER JOSE PINEDA | D203: -1626.9 | E203: D | F203: =VLOOKUP(Tabla3[[#This Row],[CONTABLE]],'SAPROV (2)'!L:M,2,FALSE) -> #N/A | H203: Productor Agro tendencias | I203: =VLOOKUP(Tabla3[[#This Row],[Deposito]],'SAPROV (2)'!D:E,2,FALSE) -> 07 | K203: COMBUSTIBLE | L203: =VLOOKUP(Tabla3[[#This Row],[PROVEEDOR]],'SAPROV (2)'!A:B,2,FALSE) -> 12 | M203: =VLOOKUP(Tabla3[[#This Row],[SERVICIO]],'SAPROV (2)'!I:J,2,FALSE) -> SERV0038 | N203: ?GASTOS COMBUSTIBLE/ GASOLINA | P203: =VLOOKUP(Tabla3[[#This Row],[FECHA]],TASA[],2,FALSE) -> 330.38 | Q203: =D203/P203 -> -4.9243296 | R203: CAJA CHICA
A204: 46034 | B204: 1896 | C204: RECARGA DE LITROS DE GASOLINA TECNICOS HENRY Y JAVIER | D204: -3139 | E204: D | F204: =VLOOKUP(Tabla3[[#This Row],[CONTABLE]],'SAPROV (2)'!L:M,2,FALSE) -> #N/A | H204: Pira café | I204: =VLOOKUP(Tabla3[[#This Row],[Deposito]],'SAPROV (2)'!D:E,2,FALSE) -> 02 | K204: COMBUSTIBLE | L204: =VLOOKUP(Tabla3[[#This Row],[PROVEEDOR]],'SAPROV (2)'!A:B,2,FALSE) -> 12 | M204: =VLOOKUP(Tabla3[[#This Row],[SERVICIO]],'SAPROV (2)'!I:J,2,FALSE) -> SERV0038 | N204: ?GASTOS COMBUSTIBLE/ GASOLINA | P204: =VLOOKUP(Tabla3[[#This Row],[FECHA]],TASA[],2,FALSE) -> 330.38 | Q204: =D204/P204 -> -9.5011805 | R204: CAJA CHICA
A205: 46034 | B205: 5438 | C205: RECARGA DE 8 LITROS DE GASOLINA TECNICO DENNY MOGOLLON | D205: -1322 | E205: D | F205: =VLOOKUP(Tabla3[[#This Row],[CONTABLE]],'SAPROV (2)'!L:M,2,FALSE) -> #N/A | H205: Pira café | I205: =VLOOKUP(Tabla3[[#This Row],[Deposito]],'SAPROV (2)'!D:E,2,FALSE) -> 02 | K205: COMBUSTIBLE | L205: =VLOOKUP(Tabla3[[#This Row],[PROVEEDOR]],'SAPROV (2)'!A:B,2,FALSE) -> 12 | M205: =VLOOKUP(Tabla3[[#This Row],[SERVICIO]],'SAPROV (2)'!I:J,2,FALSE) -> SERV0038 | N205: ?GASTOS COMBUSTIBLE/ GASOLINA | P205: =VLOOKUP(Tabla3[[#This Row],[FECHA]],TASA[],2,FALSE) -> 330.38 | Q205: =D205/P205 -> -4.0014529 | R205: CAJA CHICA
A206: 46034 | B206: 6151 | C206: RECARGA DE 20 LITROS DE GASOLINA GUARDIA NACIONAL | D206: -3304 | E206: D | F206: =VLOOKUP(Tabla3[[#This Row],[CONTABLE]],'SAPROV (2)'!L:M,2,FALSE) -> #N/A | H206: Productor Agro tendencias | I206: =VLOOKUP(Tabla3[[#This Row],[Deposito]],'SAPROV (2)'!D:E,2,FALSE) -> 07 | K206: COMBUSTIBLE | L206: =VLOOKUP(Tabla3[[#This Row],[PROVEEDOR]],'SAPROV (2)'!A:B,2,FALSE) -> 12 | M206: =VLOOKUP(Tabla3[[#This Row],[SERVICIO]],'SAPROV (2)'!I:J,2,FALSE) -> SERV0038 | N206: ?GASTOS COMBUSTIBLE/ GASOLINA | P206: =VLOOKUP(Tabla3[[#This Row],[FECHA]],TASA[],2,FALSE) -> 330.38 | Q206: =D206/P206 -> -10.000605 | R206: CAJA CHICA
A207: 46034 | B207: 6560 | C207: RECARGA DE 30 LITROS DE GASOLINA A TOYOTA HEMBRITA CAFE | D207: -4956 | E207: D | F207: =VLOOKUP(Tabla3[[#This Row],[CONTABLE]],'SAPROV (2)'!L:M,2,FALSE) -> #N/A | H207: Pira café | I207: =VLOOKUP(Tabla3[[#This Row],[Deposito]],'SAPROV (2)'!D:E,2,FALSE) -> 02 | K207: COMBUSTIBLE | L207: =VLOOKUP(Tabla3[[#This Row],[PROVEEDOR]],'SAPROV (2)'!A:B,2,FALSE) -> 12 | M207: =VLOOKUP(Tabla3[[#This Row],[SERVICIO]],'SAPROV (2)'!I:J,2,FALSE) -> SERV0038 | N207: ?GASTOS COMBUSTIBLE/ GASOLINA | P207: =VLOOKUP(Tabla3[[#This Row],[FECHA]],TASA[],2,FALSE) -> 330.38 | Q207: =D207/P207 -> -15.000908 | R207: CAJA CHICA
A208: 46035 | B208: 4655 | C208: RECARGA DE 23 LITROS DE GASOLINA CAMIONETA LK 153 | D208: -7434 | E208: D | F208: =VLOOKUP(Tabla3[[#This Row],[CONTABLE]],'SAPROV (2)'!L:M,2,FALSE) -> #N/A | H208: ADMINISTRATIVOS | I208: =VLOOKUP(Tabla3[[#This Row],[Deposito]],'SAPROV (2)'!D:E,2,FALSE) -> A01 | K208: COMBUSTIBLE | L208: =VLOOKUP(Tabla3[[#This Row],[PROVEEDOR]],'SAPROV (2)'!A:B,2,FALSE) -> 12 | M208: =VLOOKUP(Tabla3[[#This Row],[SERVICIO]],'SAPROV (2)'!I:J,2,FALSE) -> SERV0038 | N208: ?GASTOS COMBUSTIBLE/ GASOLINA | P208: =VLOOKUP(Tabla3[[#This Row],[FECHA]],TASA[],2,FALSE) -> 330.38 | Q208: =D208/P208 -> -22.501362 | R208: CAJA CHICA
... A215: 46037 | B215: 3320 | C215: RECARGA DE 112 LITROS DE GASOLINA TRITON ROJO | D215: -18991.84 | E215: D | F215: =VLOOKUP(Tabla3[[#This Row],[CONTABLE]],'SAPROV (2)'!L:M,2,FALSE) -> #N/A | H215: Productor Agro tendencias | I215: =VLOOKUP(Tabla3[[#This Row],[Deposito]],'SAPROV (2)'!D:E,2,FALSE) -> 07 | K215: COMBUSTIBLE | L215: =VLOOKUP(Tabla3[[#This Row],[PROVEEDOR]],'SAPROV (2)'!A:B,2,FALSE) -> 12 | M215: =VLOOKUP(Tabla3[[#This Row],[SERVICIO]],'SAPROV (2)'!I:J,2,FALSE) -> SERV0038 | N215: ?GASTOS COMBUSTIBLE/ GASOLINA | P215: =VLOOKUP(Tabla3[[#This Row],[FECHA]],TASA[],2,FALSE) -> 339.15 | Q215: =D215/P215 -> -55.998349 | R215: CAJA CHICA
A216: 46037 | C216: RECARGA DE 28 LITROS DE GASOLINA TRITON ROJO | D216: -4750 | E216: D | F216: =VLOOKUP(Tabla3[[#This Row],[CONTABLE]],'SAPROV (2)'!L:M,2,FALSE) -> #N/A | H216: Productor Agro tendencias | I216: =VLOOKUP(Tabla3[[#This Row],[Deposito]],'SAPROV (2)'!D:E,2,FALSE) -> 07 | K216: COMBUSTIBLE | L216: =VLOOKUP(Tabla3[[#This Row],[PROVEEDOR]],'SAPROV (2)'!A:B,2,FALSE) -> 12 | M216: =VLOOKUP(Tabla3[[#This Row],[SERVICIO]],'SAPROV (2)'!I:J,2,FALSE) -> SERV0038 | N216: ?GASTOS COMBUSTIBLE/ GASOLINA | P216: =VLOOKUP(Tabla3[[#This Row],[FECHA]],TASA[],2,FALSE) -> 339.15 | Q216: =D216/P216 -> -14.005602 | R216: CAJA CHICA
A217: 46037 | B217: 3060 | C217: RECARGA DE 39 LITROS DE GASOLINA PARA POLICIAS CUIDAR LA SIEMBRA DE CARAOTAS EN LA MAÑANA | D217: -6613.23 | E217: D | F217: =VLOOKUP(Tabla3[[#This Row],[CONTABLE]],'SAPROV (2)'!L:M,2,FALSE) -> #N/A | H217: Productor Agro tendencias | I217: =VLOOKUP(Tabla3[[#This Row],[Deposito]],'SAPROV (2)'!D:E,2,FALSE) -> 07 | K217: COMBUSTIBLE | L217: =VLOOKUP(Tabla3[[#This Row],[PROVEEDOR]],'SAPROV (2)'!A:B,2,FALSE) -> 12 | M217: =VLOOKUP(Tabla3[[#This Row],[SERVICIO]],'SAPROV (2)'!I:J,2,FALSE) -> SERV0038 | N217: ?GASTOS COMBUSTIBLE/ GASOLINA | P217: =VLOOKUP(Tabla3[[#This Row],[FECHA]],TASA[],2,FALSE) -> 339.15 | Q217: =D217/P217 -> -19.499425 | R217: CAJA CHICA
A218: 46037 | B218: 4777 | C218: RECARGA DE 31 LITROS PARA VEHICULOS DE SESAY | D218: -10425 | E218: D | F218: =VLOOKUP(Tabla3[[#This Row],[CONTABLE]],'SAPROV (2)'!L:M,2,FALSE) -> #N/A | H218: Pira café | I218: =VLOOKUP(Tabla3[[#This Row],[Deposito]],'SAPROV (2)'!D:E,2,FALSE) -> 02 | K218: COMBUSTIBLE | L218: =VLOOKUP(Tabla3[[#This Row],[PROVEEDOR]],'SAPROV (2)'!A:B,2,FALSE) -> 12 | M218: =VLOOKUP(Tabla3[[#This Row],[SERVICIO]],'SAPROV (2)'!I:J,2,FALSE) -> SERV0038 | N218: ?GASTOS COMBUSTIBLE/ GASOLINA | P218: =VLOOKUP(Tabla3[[#This Row],[FECHA]],TASA[],2,FALSE) -> 339.15 | Q218: =D218/P218 -> -30.738611 | R218: CAJA CHICA
A219: 46037 | B219: 9724 | C219: RECARGA DE 7,5LITROS PARA MOTO DENNY MOGOLLON PLACA AJ2S29T | D219: -1271.78 | E219: D | F219: =VLOOKUP(Tabla3[[#This Row],[CONTABLE]],'SAPROV (2)'!L:M,2,FALSE) -> #N/A | H219: Pira café | I219: =VLOOKUP(Tabla3[[#This Row],[Deposito]],'SAPROV (2)'!D:E,2,FALSE) -> 02 | K219: COMBUSTIBLE | L219: =VLOOKUP(Tabla3[[#This Row],[PROVEEDOR]],'SAPROV (2)'!A:B,2,FALSE) -> 12 | M219: =VLOOKUP(Tabla3[[#This Row],[SERVICIO]],'SAPROV (2)'!I:J,2,FALSE) -> SERV0038 | N219: ?GASTOS COMBUSTIBLE/ GASOLINA | P219: =VLOOKUP(Tabla3[[#This Row],[FECHA]],TASA[],2,FALSE) -> 339.15 | Q219: =D219/P219 -> -3.7499042 | R219: CAJA CHICA
A220: 46038 | B220: 1414 | C220: PAGO DE DECORACION DE CUMPLEAÑOS ING. DEISY DE ALEMAN | D220: -5126.1 | E220: D | F220: =VLOOKUP(Tabla3[[#This Row],[CONTABLE]],'SAPROV (2)'!L:M,2,FALSE) -> #N/A | H220: ADMINISTRATIVOS | I220: =VLOOKUP(Tabla3[[#This Row],[Deposito]],'SAPROV (2)'!D:E,2,FALSE) -> A01 | K220: REFRIGERIOS | L220: =VLOOKUP(Tabla3[[#This Row],[PROVEEDOR]],'SAPROV (2)'!A:B,2,FALSE) -> 13 | M220: =VLOOKUP(Tabla3[[#This Row],[SERVICIO]],'SAPROV (2)'!I:J,2,FALSE) -> SERV0033 | N220: ?GASTOS REFRIGERIOS/EMPRESA | P220: =VLOOKUP(Tabla3[[#This Row],[FECHA]],TASA[],2,FALSE) -> 341.74 | Q220: =D220/P220 -> -15 | R220: CAJA CHICA
A221: 46038 | B221: 3512 | C221: RECARGA DE 100 LITROS DE GASOLINA TRITON ROJO | D221: -17087 | E221: D | F221: =VLOOKUP(Tabla3[[#This Row],[CONTABLE]],'SAPROV (2)'!L:M,2,FALSE) -> #N/A | H221: Productor Agro tendencias | I221: =VLOOKUP(Tabla3[[#This Row],[Deposito]],'SAPROV (2)'!D:E,2,FALSE) -> 07 | K221: COMBUSTIBLE | L221: =VLOOKUP(Tabla3[[#This Row],[PROVEEDOR]],'SAPROV (2)'!A:B,2,FALSE) -> 12 | M221: =VLOOKUP(Tabla3[[#This Row],[SERVICIO]],'SAPROV (2)'!I:J,2,FALSE) -> SERV0038 | N221: ?GASTOS COMBUSTIBLE/ GASOLINA | P221: =VLOOKUP(Tabla3[[#This Row],[FECHA]],TASA[],2,FALSE) -> 341.74 | Q221: =D221/P221 -> -50 | R221: CAJA CHICA
A222: 46038 | B222: 4021 | C222: RECARGA DE 42 LITROS DE GASOLINA CAMION BLANCO | D222: -7176.54 | E222: D | F222: =VLOOKUP(Tabla3[[#This Row],[CONTABLE]],'SAPROV (2)'!L:M,2,FALSE) -> #N/A | H222: Productor Agro tendencias | I222: =VLOOKUP(Tabla3[[#This Row],[Deposito]],'SAPROV (2)'!D:E,2,FALSE) -> 07 | K222: COMBUSTIBLE | L222: =VLOOKUP(Tabla3[[#This Row],[PROVEEDOR]],'SAPROV (2)'!A:B,2,FALSE) -> 12 | M222: =VLOOKUP(Tabla3[[#This Row],[SERVICIO]],'SAPROV (2)'!I:J,2,FALSE) -> SERV0038 | N222: ?GASTOS COMBUSTIBLE/ GASOLINA | P222: =VLOOKUP(Tabla3[[#This Row],[FECHA]],TASA[],2,FALSE) -> 341.74 | Q222: =D222/P222 -> -21 | R222: CAJA CHICA
A223: 46038 | C223: RECARGA DE 20 LITROS DE GASOLINA CAMION BLANCO | D223: -3418 | E223: D | F223: =VLOOKUP(Tabla3[[#This Row],[CONTABLE]],'SAPROV (2)'!L:M,2,FALSE) -> #N/A | H223: Productor Agro tendencias | I223: =VLOOKUP(Tabla3[[#This Row],[Deposito]],'SAPROV (2)'!D:E,2,FALSE) -> 07 | K223: COMBUSTIBLE | L223: =VLOOKUP(Tabla3[[#This Row],[PROVEEDOR]],'SAPROV (2)'!A:B,2,FALSE) -> 12 | M223: =VLOOKUP(Tabla3[[#This Row],[SERVICIO]],'SAPROV (2)'!I:J,2,FALSE) -> SERV0038 | N223: ?GASTOS COMBUSTIBLE/ GASOLINA | P223: =VLOOKUP(Tabla3[[#This Row],[FECHA]],TASA[],2,FALSE) -> 341.74 | Q223: =D223/P223 -> -10.001756 | R223: CAJA CHICA
A224: 46038 | B224: 3488 | C224: RECARGA DE 55 LITROS DE GASOLINA CAMIONETA ING DEISY LK 153 | D224: -9397.85 | E224: D | F224: =VLOOKUP(Tabla3[[#This Row],[CONTABLE]],'SAPROV (2)'!L:M,2,FALSE) -> #N/A | H224: ADMINISTRATIVOS | I224: =VLOOKUP(Tabla3[[#This Row],[Deposito]],'SAPROV (2)'!D:E,2,FALSE) -> A01 | K224: COMBUSTIBLE | L224: =VLOOKUP(Tabla3[[#This Row],[PROVEEDOR]],'SAPROV (2)'!A:B,2,FALSE) -> 12 | M224: =VLOOKUP(Tabla3[[#This Row],[SERVICIO]],'SAPROV (2)'!I:J,2,FALSE) -> SERV0038 | N224: ?GASTOS COMBUSTIBLE/ GASOLINA | P224: =VLOOKUP(Tabla3[[#This Row],[FECHA]],TASA[],2,FALSE) -> 341.74 | Q224: =D224/P224 -> -27.5 | R224: CAJA CHICA
A225: 46038 | B225: 4561 - 2759 | C225: PAGO DE LAVADO DE CAMIONETA LK 153 FECHAS 9/1/2026 Y 16/1/2026 | D225: -10003.95 | E225: D | F225: =VLOOKUP(Tabla3[[#This Row],[CONTABLE]],'SAPROV (2)'!L:M,2,FALSE) -> #N/A | H225: ADMINISTRATIVOS | I225: =VLOOKUP(Tabla3[[#This Row],[Deposito]],'SAPROV (2)'!D:E,2,FALSE) -> A01 | K225: VEHICULOS | L225: =VLOOKUP(Tabla3[[#This Row],[PROVEEDOR]],'SAPROV (2)'!A:B,2,FALSE) -> 17 | M225: =VLOOKUP(Tabla3[[#This Row],[SERVICIO]],'SAPROV (2)'!I:J,2,FALSE) -> SERV0028 | N225: ?REPAR. Y MANTEN VEHIC. PERSO. MANO OBRA | P225: =VLOOKUP(Tabla3[[#This Row],[FECHA]],TASA[],2,FALSE) -> 341.74 | Q225: =D225/P225 -> -29.273571 | R225: CAJA CHICA
A226: 46038 | B226: 6829 | C226: RECARGA DE 20 LITROS DE GASOLINA TOYOTA HEMBRITA | D226: -3417.4 | E226: D | F226: =VLOOKUP(Tabla3[[#This Row],[CONTABLE]],'SAPROV (2)'!L:M,2,FALSE) -> #N/A | H226: Pira café | I226: =VLOOKUP(Tabla3[[#This Row],[Deposito]],'SAPROV (2)'!D:E,2,FALSE) -> 02 | K226: COMBUSTIBLE | L226: =VLOOKUP(Tabla3[[#This Row],[PROVEEDOR]],'SAPROV (2)'!A:B,2,FALSE) -> 12 | M226: =VLOOKUP(Tabla3[[#This Row],[SERVICIO]],'SAPROV (2)'!I:J,2,FALSE) -> SERV0038 | N226: ?GASTOS COMBUSTIBLE/ GASOLINA | P226: =VLOOKUP(Tabla3[[#This Row],[FECHA]],TASA[],2,FALSE) -> 341.74 | Q226: =D226/P226 -> -10 | R226: CAJA CHICA
A227: 46038 | B227: 8510 | C227: RECARGA DE 10 LITROS DE GASOLINA MOTO TALLER JOSE PINEDA | D227: -1708.7 | E227: D | F227: =VLOOKUP(Tabla3[[#This Row],[CONTABLE]],'SAPROV (2)'!L:M,2,FALSE) -> #N/A | H227: Productor Agro tendencias | I227: =VLOOKUP(Tabla3[[#This Row],[Deposito]],'SAPROV (2)'!D:E,2,FALSE) -> 07 | K227: COMBUSTIBLE | L227: =VLOOKUP(Tabla3[[#This Row],[PROVEEDOR]],'SAPROV (2)'!A:B,2,FALSE) -> 12 | M227: =VLOOKUP(Tabla3[[#This Row],[SERVICIO]],'SAPROV (2)'!I:J,2,FALSE) -> SERV0038 | N227: ?GASTOS COMBUSTIBLE/ GASOLINA | P227: =VLOOKUP(Tabla3[[#This Row],[FECHA]],TASA[],2,FALSE) -> 341.74 | Q227: =D227/P227 -> -5 | R227: CAJA CHICA
A228: 46038 | B228: 7234 | C228: RECARGA DE 45 LITROS DE GASOLINA.CAMIONETA GEXIBA TOVAR AJ6W18K | D228: -7690 | E228: D | F228: =VLOOKUP(Tabla3[[#This Row],[CONTABLE]],'SAPROV (2)'!L:M,2,FALSE) -> #N/A | H228: Pira Maíz | I228: =VLOOKUP(Tabla3[[#This Row],[Deposito]],'SAPROV (2)'!D:E,2,FALSE) -> 01 | K228: COMBUSTIBLE | L228: =VLOOKUP(Tabla3[[#This Row],[PROVEEDOR]],'SAPROV (2)'!A:B,2,FALSE) -> 12 | M228: =VLOOKUP(Tabla3[[#This Row],[SERVICIO]],'SAPROV (2)'!I:J,2,FALSE) -> SERV0038 | N228: ?GASTOS COMBUSTIBLE/ GASOLINA | P228: =VLOOKUP(Tabla3[[#This Row],[FECHA]],TASA[],2,FALSE) -> 341.74 | Q228: =D228/P228 -> -22.502487 | R228: CAJA CHICA
A229: 46038 | B229: 3898 | C229: RECARGA DE 20 LITROS DE GASOLINA TOYOTA HEMBRITA | D229: -3417.4 | E229: D | F229: =VLOOKUP(Tabla3[[#This Row],[CONTABLE]],'SAPROV (2)'!L:M,2,FALSE) -> #N/A | H229: Pira café | I229: =VLOOKUP(Tabla3[[#This Row],[Deposito]],'SAPROV (2)'!D:E,2,FALSE) -> 02 | K229: COMBUSTIBLE | L229: =VLOOKUP(Tabla3[[#This Row],[PROVEEDOR]],'SAPROV (2)'!A:B,2,FALSE) -> 12 | M229: =VLOOKUP(Tabla3[[#This Row],[SERVICIO]],'SAPROV (2)'!I:J,2,FALSE) -> SERV0038 | N229: ?GASTOS COMBUSTIBLE/ GASOLINA | P229: =VLOOKUP(Tabla3[[#This Row],[FECHA]],TASA[],2,FALSE) -> 341.74 | Q229: =D229/P229 -> -10 | R229: CAJA CHICA
A230: 46041 | B230: 7590 | C230: RECARGA DE LITROS DE GASOLINA TECNICOS HENRY Y JAVIER PLACA: AJ8W47E | D230: -3139 | E230: D | F230: =VLOOKUP(Tabla3[[#This Row],[CONTABLE]],'SAPROV (2)'!L:M,2,FALSE) -> #N/A | H230: Pira café | I230: =VLOOKUP(Tabla3[[#This Row],[Deposito]],'SAPROV (2)'!D:E,2,FALSE) -> 02 | K230: COMBUSTIBLE | L230: =VLOOKUP(Tabla3[[#This Row],[PROVEEDOR]],'SAPROV (2)'!A:B,2,FALSE) -> 12 | M230: =VLOOKUP(Tabla3[[#This Row],[SERVICIO]],'SAPROV (2)'!I:J,2,FALSE) -> SERV0038 | N230: ?GASTOS COMBUSTIBLE/ GASOLINA | P230: =VLOOKUP(Tabla3[[#This Row],[FECHA]],TASA[],2,FALSE) -> 344.51 | Q230: =D230/P230 -> -9.1114917 | R230: CAJA CHICA
A231: 46042 | B231: 6914 | C231: RECARGA DE 20 LITROS DE GASOLINA GUARDIA NACIONAL | D231: -3499.3 | E231: D | F231: =VLOOKUP(Tabla3[[#This Row],[CONTABLE]],'SAPROV (2)'!L:M,2,FALSE) -> #N/A | H231: Productor Agro tendencias | I231: =VLOOKUP(Tabla3[[#This Row],[Deposito]],'SAPROV (2)'!D:E,2,FALSE) -> 07 | K231: COMBUSTIBLE | L231: =VLOOKUP(Tabla3[[#This Row],[PROVEEDOR]],'SAPROV (2)'!A:B,2,FALSE) -> 12 | M231: =VLOOKUP(Tabla3[[#This Row],[SERVICIO]],'SAPROV (2)'!I:J,2,FALSE) -> SERV0038 | N231: ?GASTOS COMBUSTIBLE/ GASOLINA | P231: =VLOOKUP(Tabla3[[#This Row],[FECHA]],TASA[],2,FALSE) -> 344.51 | Q231: =D231/P231 -> -10.157325 | R231: CAJA CHICA
A232: 46042 | B232: 8747 | C232: RECARGA DE 40 LITROS DE GASOLINA URACHICHE | D232: -6950 | E232: D | F232: =VLOOKUP(Tabla3[[#This Row],[CONTABLE]],'SAPROV (2)'!L:M,2,FALSE) -> #N/A | H232: Productor Agro tendencias | I232: =VLOOKUP(Tabla3[[#This Row],[Deposito]],'SAPROV (2)'!D:E,2,FALSE) -> 07 | K232: COMBUSTIBLE | L232: =VLOOKUP(Tabla3[[#This Row],[PROVEEDOR]],'SAPROV (2)'!A:B,2,FALSE) -> 12 | M232: =VLOOKUP(Tabla3[[#This Row],[SERVICIO]],'SAPROV (2)'!I:J,2,FALSE) -> SERV0038 | N232: ?GASTOS COMBUSTIBLE/ GASOLINA | P232: =VLOOKUP(Tabla3[[#This Row],[FECHA]],TASA[],2,FALSE) -> 344.51 | Q232: =D232/P232 -> -20.17358 | R232: CAJA CHICA
A233: 46042 | B233: 2117 | C233: COMPRA DE TORTA POR CUMPLEAÑOS DE LA ING DEISY | D233: -10335.3 | E233: D | F233: =VLOOKUP(Tabla3[[#This Row],[CONTABLE]],'SAPROV (2)'!L:M,2,FALSE) -> #N/A | H233: ADMINISTRATIVOS | I233: =VLOOKUP(Tabla3[[#This Row],[Deposito]],'SAPROV (2)'!D:E,2,FALSE) -> A01 | K233: REFRIGERIOS | L233: =VLOOKUP(Tabla3[[#This Row],[PROVEEDOR]],'SAPROV (2)'!A:B,2,FALSE) -> 13 | M233: =VLOOKUP(Tabla3[[#This Row],[SERVICIO]],'SAPROV (2)'!I:J,2,FALSE) -> SERV0033 | N233: ?GASTOS REFRIGERIOS/EMPRESA | P233: =VLOOKUP(Tabla3[[#This Row],[FECHA]],TASA[],2,FALSE) -> 344.51 | Q233: =D233/P233 -> -30 | R233: CAJA CHICA
A234: 46042 | B234: 9408 | C234: RECARGA DE COMBUSTIBLE CAFE | D234: -3445.1 | E234: D | F234: =VLOOKUP(Tabla3[[#This Row],[CONTABLE]],'SAPROV (2)'!L:M,2,FALSE) -> #N/A | H234: Pira café | I234: =VLOOKUP(Tabla3[[#This Row],[Deposito]],'SAPROV (2)'!D:E,2,FALSE) -> 02 | K234: COMBUSTIBLE | L234: =VLOOKUP(Tabla3[[#This Row],[PROVEEDOR]],'SAPROV (2)'!A:B,2,FALSE) -> 12 | M234: =VLOOKUP(Tabla3[[#This Row],[SERVICIO]],'SAPROV (2)'!I:J,2,FALSE) -> SERV0038 | N234: ?GASTOS COMBUSTIBLE/ GASOLINA | P234: =VLOOKUP(Tabla3[[#This Row],[FECHA]],TASA[],2,FALSE) -> 344.51 | Q234: =D234/P234 -> -10 | R234: CAJA CHICA
A235: 46042 | B235: 9087 | C235: RECARGA DE PLATAFORMA INSAY PARA GUIAS DE MOVILIZACION | D235: -4000 | E235: D | F235: =VLOOKUP(Tabla3[[#This Row],[CONTABLE]],'SAPROV (2)'!L:M,2,FALSE) -> #N/A | H235: ADMINISTRATIVOS | I235: =VLOOKUP(Tabla3[[#This Row],[Deposito]],'SAPROV (2)'!D:E,2,FALSE) -> A01 | K235: SUNAGRO | L235: =VLOOKUP(Tabla3[[#This Row],[PROVEEDOR]],'SAPROV (2)'!A:B,2,FALSE) -> 10 | M235: =VLOOKUP(Tabla3[[#This Row],[SERVICIO]],'SAPROV (2)'!I:J,2,FALSE) -> SERV0145 | N235: GASTOS DE GUIA DE TRASLADO | P235: =VLOOKUP(Tabla3[[#This Row],[FECHA]],TASA[],2,FALSE) -> 344.51 | Q235: =D235/P235 -> -11.610693 | R235: CAJA CHICA
A236: 46043 | B236: 5276 | C236: RECARGA DE GASOLINA GUARDIA AMBIENTAL Y TECNICO HENRY ALVARADO | D236: -4341 | E236: D | F236: =VLOOKUP(Tabla3[[#This Row],[CONTABLE]],'SAPROV (2)'!L:M,2,FALSE) -> #N/A | H236: Pira café | I236: =VLOOKUP(Tabla3[[#This Row],[Deposito]],'SAPROV (2)'!D:E,2,FALSE) -> 02 | K236: COMBUSTIBLE | L236: =VLOOKUP(Tabla3[[#This Row],[PROVEEDOR]],'SAPROV (2)'!A:B,2,FALSE) -> 12 | M236: =VLOOKUP(Tabla3[[#This Row],[SERVICIO]],'SAPROV (2)'!I:J,2,FALSE) -> SERV0038 | N236: ?GASTOS COMBUSTIBLE/ GASOLINA | P236: =VLOOKUP(Tabla3[[#This Row],[FECHA]],TASA[],2,FALSE) -> 347.26 | Q236: =D236/P236 -> -12.50072 | R236: CAJA CHICA
A237: 46043 | B237: 5630 | C237: RECARGA DE 20 LITROS DE GASOLINA TOYOTA HEMBRITA | D237: -3475 | E237: D | F237: =VLOOKUP(Tabla3[[#This Row],[CONTABLE]],'SAPROV (2)'!L:M,2,FALSE) -> #N/A | H237: Pira café | I237: =VLOOKUP(Tabla3[[#This Row],[Deposito]],'SAPROV (2)'!D:E,2,FALSE) -> 02 | K237: COMBUSTIBLE | L237: =VLOOKUP(Tabla3[[#This Row],[PROVEEDOR]],'SAPROV (2)'!A:B,2,FALSE) -> 12 | M237: =VLOOKUP(Tabla3[[#This Row],[SERVICIO]],'SAPROV (2)'!I:J,2,FALSE) -> SERV0038 | N237: ?GASTOS COMBUSTIBLE/ GASOLINA | P237: =VLOOKUP(Tabla3[[#This Row],[FECHA]],TASA[],2,FALSE) -> 347.26 | Q237: =D237/P237 -> -10.006911 | R237: CAJA CHICA
... A254: 46049 | B254: 4700 | C254: RECARGA DE 140 LITROS DE GASOLINA PARA EL TRITON ROJO (EMISAEL) | D254: -25124.4 | E254: D | F254: =VLOOKUP(Tabla3[[#This Row],[CONTABLE]],'SAPROV (2)'!L:M,2,FALSE) -> #N/A | H254: Productor Agro tendencias | I254: =VLOOKUP(Tabla3[[#This Row],[Deposito]],'SAPROV (2)'!D:E,2,FALSE) -> 07 | K254: COMBUSTIBLE | L254: =VLOOKUP(Tabla3[[#This Row],[PROVEEDOR]],'SAPROV (2)'!A:B,2,FALSE) -> 12 | M254: =VLOOKUP(Tabla3[[#This Row],[SERVICIO]],'SAPROV (2)'!I:J,2,FALSE) -> SERV0038 | N254: ?GASTOS COMBUSTIBLE/ GASOLINA | P254: =VLOOKUP(Tabla3[[#This Row],[FECHA]],TASA[],2,FALSE) -> 358.92 | Q254: =D254/P254 -> -70 | R254: CAJA CHICA
A255: 46049 | C255: RECARGA DE 40 LITROS DE COMBUSTIBLE PERSONAL DEL SESAY | D255: -7178.4 | E255: D | F255: =VLOOKUP(Tabla3[[#This Row],[CONTABLE]],'SAPROV (2)'!L:M,2,FALSE) -> #N/A | H255: Pira café | I255: =VLOOKUP(Tabla3[[#This Row],[Deposito]],'SAPROV (2)'!D:E,2,FALSE) -> 02 | K255: COMBUSTIBLE | L255: =VLOOKUP(Tabla3[[#This Row],[PROVEEDOR]],'SAPROV (2)'!A:B,2,FALSE) -> 12 | M255: =VLOOKUP(Tabla3[[#This Row],[SERVICIO]],'SAPROV (2)'!I:J,2,FALSE) -> SERV0038 | N255: ?GASTOS COMBUSTIBLE/ GASOLINA | P255: =VLOOKUP(Tabla3[[#This Row],[FECHA]],TASA[],2,FALSE) -> 358.92 | Q255: =D255/P255 -> -20 | R255: CAJA CHICA
A256: 46050 | B256: 8500-1715 | C256: RECARGA DE 20 LITROS DE GASOLINA TOYOTA HEMBRITA Y COMPRA DE 2 INYECTADORAS | D256: -3832.26 | E256: D | F256: =VLOOKUP(Tabla3[[#This Row],[CONTABLE]],'SAPROV (2)'!L:M,2,FALSE) -> #N/A | H256: Pira café | I256: =VLOOKUP(Tabla3[[#This Row],[Deposito]],'SAPROV (2)'!D:E,2,FALSE) -> 02 | K256: COMBUSTIBLE | L256: =VLOOKUP(Tabla3[[#This Row],[PROVEEDOR]],'SAPROV (2)'!A:B,2,FALSE) -> 12 | M256: =VLOOKUP(Tabla3[[#This Row],[SERVICIO]],'SAPROV (2)'!I:J,2,FALSE) -> SERV0038 | N256: ?GASTOS COMBUSTIBLE/ GASOLINA | P256: =VLOOKUP(Tabla3[[#This Row],[FECHA]],TASA[],2,FALSE) -> 361.49 | Q256: =D256/P256 -> -10.601289 | R256: CAJA CHICA
A257: 46050 | B257: 3272 | C257: RECARGA DE 44 LITROS DE GASOLINA CAMIONETA SR GEXIBA | D257: -7952.78 | E257: D | F257: =VLOOKUP(Tabla3[[#This Row],[CONTABLE]],'SAPROV (2)'!L:M,2,FALSE) -> #N/A | H257: Pira Maíz | I257: =VLOOKUP(Tabla3[[#This Row],[Deposito]],'SAPROV (2)'!D:E,2,FALSE) -> 01 | K257: COMBUSTIBLE | L257: =VLOOKUP(Tabla3[[#This Row],[PROVEEDOR]],'SAPROV (2)'!A:B,2,FALSE) -> 12 | M257: =VLOOKUP(Tabla3[[#This Row],[SERVICIO]],'SAPROV (2)'!I:J,2,FALSE) -> SERV0038 | N257: ?GASTOS COMBUSTIBLE/ GASOLINA | P257: =VLOOKUP(Tabla3[[#This Row],[FECHA]],TASA[],2,FALSE) -> 361.49 | Q257: =D257/P257 -> -22 | R257: CAJA CHICA
A258: 46050 | B258: 1429 | C258: RECARGA DE 50 LITROS DE GASOLINA PARA EL TRITON ROJO (JESUS) | D258: -9038 | E258: D | F258: =VLOOKUP(Tabla3[[#This Row],[CONTABLE]],'SAPROV (2)'!L:M,2,FALSE) -> #N/A | H258: Productor Agro tendencias | I258: =VLOOKUP(Tabla3[[#This Row],[Deposito]],'SAPROV (2)'!D:E,2,FALSE) -> 07 | K258: COMBUSTIBLE | L258: =VLOOKUP(Tabla3[[#This Row],[PROVEEDOR]],'SAPROV (2)'!A:B,2,FALSE) -> 12 | M258: =VLOOKUP(Tabla3[[#This Row],[SERVICIO]],'SAPROV (2)'!I:J,2,FALSE) -> SERV0038 | N258: ?GASTOS COMBUSTIBLE/ GASOLINA | P258: =VLOOKUP(Tabla3[[#This Row],[FECHA]],TASA[],2,FALSE) -> 361.49 | Q258: =D258/P258 -> -25.002075 | R258: CAJA CHICA
A259: 46050 | B259: 1013-2905 | C259: RECARGA DE 51 LITROS DE GASOLINA CAMIONETA SR GEXIBA | D259: -9218 | E259: D | F259: =VLOOKUP(Tabla3[[#This Row],[CONTABLE]],'SAPROV (2)'!L:M,2,FALSE) -> #N/A | H259: Pira Maíz | I259: =VLOOKUP(Tabla3[[#This Row],[Deposito]],'SAPROV (2)'!D:E,2,FALSE) -> 01 | K259: COMBUSTIBLE | L259: =VLOOKUP(Tabla3[[#This Row],[PROVEEDOR]],'SAPROV (2)'!A:B,2,FALSE) -> 12 | M259: =VLOOKUP(Tabla3[[#This Row],[SERVICIO]],'SAPROV (2)'!I:J,2,FALSE) -> SERV0038 | N259: ?GASTOS COMBUSTIBLE/ GASOLINA | P259: =VLOOKUP(Tabla3[[#This Row],[FECHA]],TASA[],2,FALSE) -> 361.49 | Q259: =D259/P259 -> -25.500014 | R259: CAJA CHICA
A260: 46051 | B260: 3203 | C260: RECARGA DE 30 LITROS DE GASOLINA TOYOTA HEMBRITA | D260: -5454.9 | E260: D | F260: =VLOOKUP(Tabla3[[#This Row],[CONTABLE]],'SAPROV (2)'!L:M,2,FALSE) -> #N/A | H260: Pira café | I260: =VLOOKUP(Tabla3[[#This Row],[Deposito]],'SAPROV (2)'!D:E,2,FALSE) -> 02 | K260: COMBUSTIBLE | L260: =VLOOKUP(Tabla3[[#This Row],[PROVEEDOR]],'SAPROV (2)'!A:B,2,FALSE) -> 12 | M260: =VLOOKUP(Tabla3[[#This Row],[SERVICIO]],'SAPROV (2)'!I:J,2,FALSE) -> SERV0038 | N260: ?GASTOS COMBUSTIBLE/ GASOLINA | P260: =VLOOKUP(Tabla3[[#This Row],[FECHA]],TASA[],2,FALSE) -> 363.66 | Q260: =D260/P260 -> -15 | R260: CAJA CHICA
A261: 46051 | B261: 4715 | C261: RECARGA DE 50 LITROS DE GASOLINA CAMIONETA LK 153 | D261: -9091.5 | E261: D | F261: =VLOOKUP(Tabla3[[#This Row],[CONTABLE]],'SAPROV (2)'!L:M,2,FALSE) -> #N/A | H261: ADMINISTRATIVOS | I261: =VLOOKUP(Tabla3[[#This Row],[Deposito]],'SAPROV (2)'!D:E,2,FALSE) -> A01 | K261: COMBUSTIBLE | L261: =VLOOKUP(Tabla3[[#This Row],[PROVEEDOR]],'SAPROV (2)'!A:B,2,FALSE) -> 12 | M261: =VLOOKUP(Tabla3[[#This Row],[SERVICIO]],'SAPROV (2)'!I:J,2,FALSE) -> SERV0038 | N261: ?GASTOS COMBUSTIBLE/ GASOLINA | P261: =VLOOKUP(Tabla3[[#This Row],[FECHA]],TASA[],2,FALSE) -> 363.66 | Q261: =D261/P261 -> -25 | R261: CAJA CHICA
A262: 46052 | B262: 9842 | C262: RECARGA DE 70 LITROS DE GASOLINA AL CAMION BLANCO (OSCAR OROPEZA) | D262: -12856 | E262: D | F262: =VLOOKUP(Tabla3[[#This Row],[CONTABLE]],'SAPROV (2)'!L:M,2,FALSE) -> #N/A | H262: Productor Agro tendencias | I262: =VLOOKUP(Tabla3[[#This Row],[Deposito]],'SAPROV (2)'!D:E,2,FALSE) -> 07 | K262: COMBUSTIBLE | L262: =VLOOKUP(Tabla3[[#This Row],[PROVEEDOR]],'SAPROV (2)'!A:B,2,FALSE) -> 12 | M262: =VLOOKUP(Tabla3[[#This Row],[SERVICIO]],'SAPROV (2)'!I:J,2,FALSE) -> SERV0038 | N262: ?GASTOS COMBUSTIBLE/ GASOLINA | P262: =VLOOKUP(Tabla3[[#This Row],[FECHA]],TASA[],2,FALSE) -> 367.31 | Q262: =D262/P262 -> -35.000408 | R262: CAJA CHICA
A263: 46052 | B263: 7287 | C263: RECARGA DE 120 LITROS DE GASOLINA TRITON TOJO (JESUS SUEREZ) | D263: -22039 | E263: D | F263: =VLOOKUP(Tabla3[[#This Row],[CONTABLE]],'SAPROV (2)'!L:M,2,FALSE) -> #N/A | H263: Productor Agro tendencias | I263: =VLOOKUP(Tabla3[[#This Row],[Deposito]],'SAPROV (2)'!D:E,2,FALSE) -> 07 | K263: COMBUSTIBLE | L263: =VLOOKUP(Tabla3[[#This Row],[PROVEEDOR]],'SAPROV (2)'!A:B,2,FALSE) -> 12 | M263: =VLOOKUP(Tabla3[[#This Row],[SERVICIO]],'SAPROV (2)'!I:J,2,FALSE) -> SERV0038 | N263: ?GASTOS COMBUSTIBLE/ GASOLINA | P263: =VLOOKUP(Tabla3[[#This Row],[FECHA]],TASA[],2,FALSE) -> 367.31 | Q263: =D263/P263 -> -60.001089 | R263: CAJA CHICA
A264: 46052 | B264: 9062 | C264: PAGO DE ENVIO DE FACTURA AGROCELTA | D264: -858.94 | E264: D | F264: =VLOOKUP(Tabla3[[#This Row],[CONTABLE]],'SAPROV (2)'!L:M,2,FALSE) -> #N/A | H264: Productor Agro tendencias | I264: =VLOOKUP(Tabla3[[#This Row],[Deposito]],'SAPROV (2)'!D:E,2,FALSE) -> 07 | K264: FLETES | L264: =VLOOKUP(Tabla3[[#This Row],[PROVEEDOR]],'SAPROV (2)'!A:B,2,FALSE) -> 39 | M264: =VLOOKUP(Tabla3[[#This Row],[SERVICIO]],'SAPROV (2)'!I:J,2,FALSE) -> SERV0049 | N264: ?FLETES | P264: =VLOOKUP(Tabla3[[#This Row],[FECHA]],TASA[],2,FALSE) -> 367.31 | Q264: =D264/P264 -> -2.3384607 | R264: CAJA CHICA
A265: 46053 | B265: 1200 | C265: COMPRA DE ESTANTILLOS PARA CERCA | D265: -18365.35 | E265: D | F265: =VLOOKUP(Tabla3[[#This Row],[CONTABLE]],'SAPROV (2)'!L:M,2,FALSE) -> #N/A | H265: Productor Agro tendencias | I265: =VLOOKUP(Tabla3[[#This Row],[Deposito]],'SAPROV (2)'!D:E,2,FALSE) -> 07 | K265: CONSTRUCCION | L265: =VLOOKUP(Tabla3[[#This Row],[PROVEEDOR]],'SAPROV (2)'!A:B,2,FALSE) -> 20 | M265: =VLOOKUP(Tabla3[[#This Row],[SERVICIO]],'SAPROV (2)'!I:J,2,FALSE) -> SERV0058E | N265: ?MANTENIMIENTO INSTALACIONES (E) | P265: =VLOOKUP(Tabla3[[#This Row],[FECHA]],TASA[],2,FALSE) -> 370.25 | Q265: =D265/P265 -> -49.602566 | R265: CAJA CHICA
A266: 46023 | B266: 120200011331 | C266: COM MANTENIMIENTO DE CUENTA | D266: -8 | E266: D | F266: =VLOOKUP(Tabla3[[#This Row],[CONTABLE]],'SAPROV (2)'!L:M,2,FALSE) -> #N/A | H266: ADMINISTRATIVOS | I266: =VLOOKUP(Tabla3[[#This Row],[Deposito]],'SAPROV (2)'!D:E,2,FALSE) -> A01 | K266: COMISIONES BANCARIAS | L266: =VLOOKUP(Tabla3[[#This Row],[PROVEEDOR]],'SAPROV (2)'!A:B,2,FALSE) -> 04 | M266: =VLOOKUP(Tabla3[[#This Row],[SERVICIO]],'SAPROV (2)'!I:J,2,FALSE) -> SERV0060 | N266: ?COMISIONES BANCARIAS | P266: =VLOOKUP(Tabla3[[#This Row],[FECHA]],TASA[],2,FALSE) -> 301.37 | Q266: =D266/P266 -> -0.026545442 | R266: VENEZUELA
A267: 46027 | B267: 676213121001 | C267: COMISION PAGO A PROVEEDORES | D267: -2500 | E267: D | F267: =VLOOKUP(Tabla3[[#This Row],[CONTABLE]],'SAPROV (2)'!L:M,2,FALSE) -> #N/A | H267: ADMINISTRATIVOS | I267: =VLOOKUP(Tabla3[[#This Row],[Deposito]],'SAPROV (2)'!D:E,2,FALSE) -> A01 | K267: COMISIONES BANCARIAS | L267: =VLOOKUP(Tabla3[[#This Row],[PROVEEDOR]],'SAPROV (2)'!A:B,2,FALSE) -> 04 | M267: =VLOOKUP(Tabla3[[#This Row],[SERVICIO]],'SAPROV (2)'!I:J,2,FALSE) -> SERV0060 | N267: ?COMISIONES BANCARIAS | P267: =VLOOKUP(Tabla3[[#This Row],[FECHA]],TASA[],2,FALSE) -> 304.68 | Q267: =D267/P267 -> -8.2053302 | R267: VENEZUELA
A268: 46027 | B268: 676213857005 | C268: COMISION PAGO A PROVEEDORES | D268: -2500 | E268: D | F268: =VLOOKUP(Tabla3[[#This Row],[CONTABLE]],'SAPROV (2)'!L:M,2,FALSE) -> #N/A | H268: ADMINISTRATIVOS | I268: =VLOOKUP(Tabla3[[#This Row],[Deposito]],'SAPROV (2)'!D:E,2,FALSE) -> A01 | K268: COMISIONES BANCARIAS | L268: =VLOOKUP(Tabla3[[#This Row],[PROVEEDOR]],'SAPROV (2)'!A:B,2,FALSE) -> 04 | M268: =VLOOKUP(Tabla3[[#This Row],[SERVICIO]],'SAPROV (2)'!I:J,2,FALSE) -> SERV0060 | N268: ?COMISIONES BANCARIAS | P268: =VLOOKUP(Tabla3[[#This Row],[FECHA]],TASA[],2,FALSE) -> 304.68 | Q268: =D268/P268 -> -8.2053302 | R268: VENEZUELA
A269: 46027 | B269: 676217619025 | C269: COMISION PAGO A PROVEEDORES | D269: -2500 | E269: D | F269: =VLOOKUP(Tabla3[[#This Row],[CONTABLE]],'SAPROV (2)'!L:M,2,FALSE) -> #N/A | H269: ADMINISTRATIVOS | I269: =VLOOKUP(Tabla3[[#This Row],[Deposito]],'SAPROV (2)'!D:E,2,FALSE) -> A01 | K269: COMISIONES BANCARIAS | L269: =VLOOKUP(Tabla3[[#This Row],[PROVEEDOR]],'SAPROV (2)'!A:B,2,FALSE) -> 04 | M269: =VLOOKUP(Tabla3[[#This Row],[SERVICIO]],'SAPROV (2)'!I:J,2,FALSE) -> SERV0060 | N269: ?COMISIONES BANCARIAS | P269: =VLOOKUP(Tabla3[[#This Row],[FECHA]],TASA[],2,FALSE) -> 304.68 | Q269: =D269/P269 -> -8.2053302 | R269: VENEZUELA
A270: 46027 | B270: 676214399008 | C270: COMISION PAGO A PROVEEDORES | D270: -2500 | E270: D | F270: =VLOOKUP(Tabla3[[#This Row],[CONTABLE]],'SAPROV (2)'!L:M,2,FALSE) -> #N/A | H270: ADMINISTRATIVOS | I270: =VLOOKUP(Tabla3[[#This Row],[Deposito]],'SAPROV (2)'!D:E,2,FALSE) -> A01 | K270: COMISIONES BANCARIAS | L270: =VLOOKUP(Tabla3[[#This Row],[PROVEEDOR]],'SAPROV (2)'!A:B,2,FALSE) -> 04 | M270: =VLOOKUP(Tabla3[[#This Row],[SERVICIO]],'SAPROV (2)'!I:J,2,FALSE) -> SERV0060 | N270: ?COMISIONES BANCARIAS | P270: =VLOOKUP(Tabla3[[#This Row],[FECHA]],TASA[],2,FALSE) -> 304.68 | Q270: =D270/P270 -> -8.2053302 | R270: VENEZUELA
A271: 46027 | B271: 676217432024 | C271: COMISION PAGO A PROVEEDORES | D271: -2500 | E271: D | F271: =VLOOKUP(Tabla3[[#This Row],[CONTABLE]],'SAPROV (2)'!L:M,2,FALSE) -> #N/A | H271: ADMINISTRATIVOS | I271: =VLOOKUP(Tabla3[[#This Row],[Deposito]],'SAPROV (2)'!D:E,2,FALSE) -> A01 | K271: COMISIONES BANCARIAS | L271: =VLOOKUP(Tabla3[[#This Row],[PROVEEDOR]],'SAPROV (2)'!A:B,2,FALSE) -> 04 | M271: =VLOOKUP(Tabla3[[#This Row],[SERVICIO]],'SAPROV (2)'!I:J,2,FALSE) -> SERV0060 | N271: ?COMISIONES BANCARIAS | P271: =VLOOKUP(Tabla3[[#This Row],[FECHA]],TASA[],2,FALSE) -> 304.68 | Q271: =D271/P271 -> -8.2053302 | R271: VENEZUELA
... A682: 46042 | B682: 60196735 | C682: COMISION PAGO A PROVEE OTROS B | D682: -793.66 | E682: D | F682: =VLOOKUP(Tabla3[[#This Row],[CONTABLE]],'SAPROV (2)'!L:M,2,FALSE) -> #N/A | H682: ADMINISTRATIVOS | I682: =VLOOKUP(Tabla3[[#This Row],[Deposito]],'SAPROV (2)'!D:E,2,FALSE) -> A01 | K682: COMISIONES BANCARIAS | L682: =VLOOKUP(Tabla3[[#This Row],[PROVEEDOR]],'SAPROV (2)'!A:B,2,FALSE) -> 04 | M682: =VLOOKUP(Tabla3[[#This Row],[SERVICIO]],'SAPROV (2)'!I:J,2,FALSE) -> SERV0060 | N682: ?COMISIONES BANCARIAS | P682: =VLOOKUP(Tabla3[[#This Row],[FECHA]],TASA[],2,FALSE) -> 344.51 | Q682: =D682/P682 -> -2.3037357 | R682: TESORO
A683: 46042 | C683: COMIS FIANZA GRTIA COMERCIALES | D683: -550120.25 | E683: D | F683: =VLOOKUP(Tabla3[[#This Row],[CONTABLE]],'SAPROV (2)'!L:M,2,FALSE) -> #N/A | H683: ADMINISTRATIVOS | I683: =VLOOKUP(Tabla3[[#This Row],[Deposito]],'SAPROV (2)'!D:E,2,FALSE) -> A01 | K683: COMISIONES BANCARIAS | L683: =VLOOKUP(Tabla3[[#This Row],[PROVEEDOR]],'SAPROV (2)'!A:B,2,FALSE) -> 04 | M683: =VLOOKUP(Tabla3[[#This Row],[SERVICIO]],'SAPROV (2)'!I:J,2,FALSE) -> SERV0060 | N683: ?COMISIONES BANCARIAS | P683: =VLOOKUP(Tabla3[[#This Row],[FECHA]],TASA[],2,FALSE) -> 344.51 | Q683: =D683/P683 -> -1596.8194 | R683: TESORO
...

Sheet SAPROV (2)
A1: ACRILICOS VIRGUEZ, C.A. | B1: J-085083766 | D1: Pira café | E1: 02 | G1: Campaña | I1: ? ADQUSICION DE HERRAMIENTAS/TALLER | J1: SERV0020 | L1: CAJA PUENTE TRANSITORIA | M1: 110101001
A2: ADQUISION | B2: 47 | D2: Pira Caraota | E2: 03 | I2: ? ADQUSICION DE HERRAMIENTAS/TALLER | J2: SERV0020E | L2: CARGOS TRANSITORIOS TRASPASO | M2: 110101003
A3: AGRICOLA NOVATERRA | B3: J500597193 | D3: Pira Arroz | E3: 04 | I3: ?ADQUISICION BIENES INMUEBLES | J3: SERV0056 | L3: BANCO DEL TESORO | M3: 110102001
A4: AGROFERRETERIA CAMPO ALEGRE | B4: J296883335 | D4: no usar | E4: 05 | I4: ?ADQUISICION BIENES INMUEBLES | J4: SERV0056E | L4: BANESCO | M4: 110102002
A5: AGROPACA | B5: J412594982 | D5: Leguminosa | E5: 06 | I5: ?ADQUISICION BIENES MUEBLES | J5: SERV0057 | L5: PROVINCIAL | M5: 110102003
A6: AGROPECUARIA LAS DOS QUEBRADAS | B6: J308039209 | D6: Exportacion | E6: 08 | I6: ?ADQUISICION BIENES MUEBLES | J6: SERV0057E | L6: BANCO DE VENEZUELA | M6: 110102004
A7: AGROPLUS VENEZUELA C.A | B7: J-50044103-7 | D7: ADMINISTRATIVOS | E7: A01 | I7: ?ADQUISICION DE EQUIPOS DE LABORATORIO | J7: SERV0128 | L7: BANCO NACIONAL DE CREDITO BNC | M7: 110102005
A8: AGROTOTAL 2011, SA | B8: J-400085799 | D8: Pira Maíz | E8: 01 | I8: ?ADQUISICION DE EQUIPOS DE LABORATORIO | J8: SERV0128E | L8: BICENTENARIO AGRO | M8: 110102006
A9: ALCALDIA | B9: 09 | D9: Productor Agro tendencias | E9: 07 | I9: ?ADQUISICION MOBILIARIO | J9: SERV0055 | L9: MERCANTIL AGRO | M9: 110102007
A10: ALCALDIA URACHICHE | B10: G200045507 | D10: no usar | E10: 09 | I10: ?ADQUISICION MOBILIARIO | J10: SERV0055E | L10: TITULO DE COBERTURA BANESCO | M10: 110105001
A11: ALEXI FRANCISCO QUINTERO | B11: V047314000 | I11: ?BENEFICIO ALIMENTICIO | J11: SERV0202 | L11: TITULO DE COBERTURA TESORO | M11: 110105004
A12: ALISMERI ROJAS | B12: V20468697 | I12: ?BENEFICIO ALIMENTICIO | J12: SERV0202E | L12: TITULO DE COBERTURA BICENTENARIO | M12: 110105005
A13: ANGEL MORALES | B13: V22314455 | I13: ?CARGA Y DESGARGA DE GANDOLA | J13: SERV0207 | L13: CUENTAS POR COBRAR CLIENTES | M13: 110106001
A14: ANGEL SILVA | B14: 73 | I14: ?CARGA Y DESGARGA DE GANDOLA | J14: SERV0207E | L14: CUENTAS POR COBRAR HERAS NEW FASHION | M14: 110106012
A15: ANGEL SILVA | B15: V199723873 | I15: ?COMISIONES BANCARIAS | J15: SERV0060 | L15: CUENTAS POR COBRAR TENDENCIAS AB, C.A. | M15: 110106013
A16: ANGELA ILARRAZA | B16: V4772646 | I16: ?COMISIONES BANCARIAS | J16: SERV0060E | L16: CUENTAS POR COBRAR INDUSTRIA AGROTENDENCIAS | M16: 110106019
A17: ANSWERS TECNIT SERVIT, C.A | B17: J-400489326 | I17: ?COMISIONES ESPECIALES | J17: SERV0068 | L17: CUENTAS POR COBRAR SILOS AGROTENDENCIAS | M17: 110106025
A18: ANTIOQUIO GALINDEZ | B18: V7550846 | I18: ?COMISIONES ESPECIALES | J18: SERV0068E | L18: CUENTAS POR COBRAR CLIENTES | M18: 110106099
A19: ANTONIO DURAN | B19: V6701712 | I19: ?COMPRA DE SEMILLA | J19: SERV0148 | L19: CUENTAS POR COBRAR PROVEEDORES | M19: 110107001
A20: ANYELBI DAVID GALINDEZ | B20: V20320699 | I20: ?COMPRA DE SEMILLA | J20: SERV0148E | L20: EFECTOS POR COBRAR | M20: 110110001
A21: ARACAL/CIARA | B21: 71 | I21: ?COMPRA FERTILIZANTE | J21: SERV0149E | L21: CUENTAS POR COBRAR EMPLEADOS | M21: 110113001
A22: ARCILIO DURAN | B22: 16261437 | I22: ?COMPRA VEHICULO/ACTIVO | J22: SERV0066 | L22: ANTICIPO PROVEDORES | M22: 110114001
... A225: ORGANISMOS GUBERNAMENTALES | B225: 40 | I225: IMPUESTO IGTF (pago divisas) | J225: SERV0127E | L225: ADQUISICION DE MAQUINARIA | M225: 730101028
A226: ORINOCO GRILL C.A | B226: J402118317 | L226: MANTENIMIENTO DE MAQUINARIAS INSUMOS | M226: 730101029
A227: ORINOCO GRILL C.A | B227: J50128967-0 | L227: MANTENIMIENTO MAQUINARIAS MANO DE OBRA | M227: 730101030
A228: ORVAL SA | B228: J307387831 | L228: FERTILIZANTES | M228: 730101031
A229: OSWALDO COLMENAREZ | B229: V7437664 | L229: GASTOS TRAMITES BOMBEROS | M229: 730101032
A230: OVIDIO PALERMO | B230: V11652864 | L230: GASTOS ARACAL/CIARA | M230: 730101033
A231: PABLO GERARDO LEON GUAREMAL MOTOS | B231: V108576908 | L231: GASTOS NOTARIAS | M231: 730101034
A232: PAGO EFECTIVO | B232: 34 | L232: ADQUISICION DE INMUEBLE | M232: 730101035
A233: PARAFISCALES | B233: 03 | L233: ADQUISICION DE BIENES MUEBLES | M233: 730101036
A234: PERMISOS | B234: 08 | L234: PREMIO MOVILIDAD | M234: 730101037
A235: PLASTISERIES C.A | B235: J310141932 | L235: INSUMOS TALLER | M235: 730101038
A236: PRESTAMOS | B236: 46 | L236: BONO COMPLEMENTARIO | M236: 740101001
A237: PRODUCCION | B237: 22 | L237: SALARIO BASE QUINCENAL | M237: 740101002
... A240: PUBLICIDAD | B240: 30 | L240: DESCUENTO POR FINANCIAMIENTO | M240: 840101003
A241: QUALITY MOTORS , C.A | B241: J-409850129
A242: RAFAEL OSCAR PACHECO CASTILLO | B242: V115207519
A243: REFRIGERIOS | B243: 13
A244: REPRESENTACIONES LUIMAR CA | B244: J304837666
A245: REPUESTOS HRN 2020 CA | B245: J500673124
A246: RIGOBERTA DURAN | B246: V7677659
A247: ROBERT NAVAS | B247: V23570444
A248: ROSA MUJICA | B248: V17319940
A249: RUBY CENSINA IANNELLI DE CARMONA | B249: V075071856
A250: RUEDA DE NEGOCIOS | B250: 19
A251: SEGURIDAD | B251: 41
A252: SELLOS HIDRAULICOS CA | B252: J317378849
... A282: YONNY JUAREZ | B282: V16974383

Sheet TASA
B3: FECHA | C3: TASA
B4: 46023 | C4: 301.37
B5: 46024 | C5: 301.37
B6: 46025 | C6: 304.68
B7: 46026 | C7: 304.68
B8: 46027 | C8: 304.68
B9: 46028 | C9: 308.15
B10: 46029 | C10: 311.88
B11: 46030 | C11: 321.03
B12: 46031 | C12: 325.39
B13: 46032 | C13: 330.38
B14: 46033 | C14: 330.38
B15: 46034 | C15: 330.38
... B34: 46053 | C34: 370.25
